Workbook
Name _1: #REF!
Name _1: #REF!
Name _1: #REF!
Name _1: #REF!
Name _1: #REF!
Name _1: #REF!
Name _1: #REF!
Name _1: #REF!
Name _1: #REF!
Name _1: #REF!
Name _1: #REF!
Name _1: #REF!
Name _1: #REF!
Name _10: #REF!
Name _10: #REF!
Name _10: #REF!
Name _10: #REF!
Name _10: #REF!
Name _10: #REF!
Name _10: #REF!
Name _10: #REF!
Name _10: #REF!
Name _10: #REF!
Name _10: #REF!
Name _10: #REF!
Name _10: #REF!
Name _11: #REF!
Name _11: #REF!
Name _11: #REF!
Name _11: #REF!
Name _11: #REF!
Name _11: #REF!
Name _11: #REF!
Name _11: #REF!
Name _11: #REF!
Name _11: #REF!
Name _11: #REF!
Name _11: #REF!
Name _11: #REF!
Name _12: #REF!
Name _12: #REF!
Name _12: #REF!
Name _12: #REF!
Name _12: #REF!
Name _12: #REF!
Name _12: #REF!
Name _12: #REF!
Name _12: #REF!
Name _12: #REF!
Name _12: #REF!
Name _12: #REF!
Name _12: #REF!
Name _13: #REF!
Name _13: #REF!
Name _13: #REF!
Name _13: #REF!
Name _13: #REF!
Name _13: #REF!
Name _13: #REF!
Name _13: #REF!

Sheet Grand Summary
A2: THE GOVERNMENT OF THE HONG KONG SPECIAL ADMINISTRATIVE REGION
A4: HIGHWAYS DEPARTMENT
A5: MAJOR WORKS PROJECT MANAGEMENT OFFICE
A7: CONTRACT NO. HY/2022/14
A8: MODIFICATION WORKS OF NOISE BARRIERS ALONG YUEN LONG HIGHWAY NEAR PARK SIGNATURE
A10: GRAND SUMMARY OF
A11: THE ACTIVITY SCHEDULE
A13: Page | B13: Description | J13: Amount (HK$)
A14: AS.S1/16 | C14: Schedule No. 1 - Preliminaries | J14: $
A15: AS.S2/01 | C15: Schedule No. 2 - Preservation and Protection of Trees | J15: $
A16: AS.S3/05 | C16: Schedule No. 3 - Modification Works of Noise Barriers | J16: $
A17: AS.S4/03 | C17: Schedule No. 4 - Monitoring Payment of Wages | J17: $
A18: AS.S5/10 | C18: Schedule No. 5 - Site Safety | J18: $ | K18: ='A5'!K630 -> 252780
A19: AS.S6/03 | C19: Schedule No. 6 - Site Cleanliness and Tidiness | J19: $ | K19: ='A6'!K204 -> 419322
C42: Sub-total of above (A) | J42: $
C43: Tendered total of the Prices = (A) [To be carried to the Form of Tender and the Contract Data Part two subject to the correction rules for tender errors as set out in Clause GCT 11 of the General Conditions of Tender] | J43: $
C44: Contingency sum for Defined Cost for compensation events* (B) | J44: $ | K44: 2100000
C45: Contingency sum for Fee for compensation events* (C) = (B) x fee percentage inserted by the tenderer in the Contract Data Part two | J45: $
C46: Provisional sum for price adjustment for inflation under Secondary Option X1* (D) | J46: $ | K46: 945000
C47: Provisional sum for performance‐tied payment item under Pay for Safety Performance Merit Scheme (PFSPMS) under Secondary Option X20* (E) | J47: $ | K47: 336188
C48: Sub‐total of all contingency sums and provisional sums above* (F) = (B) + (C) + (D) + (E)
C49: Forecast total of the Prices for tender evaluation purpose* (G) = (A) + (F) | J49: To be completed by the Project Manager designate after receipt of tender
A51: *Remarks: The contingency sums, provisional sums and forecast total of the Prices shall not form part of this contract. Please refer to Clause [A7] of the additional conditions of contract.
A52: (1) The contingency sums, provisional sums and forecast total of the Prices shall not form part of the contract. Please refer to Clause A7 of the additional conditions of contract.
B55: Signature of person authorised
B56: to sign on behalf of tenderer : | G56: ……………………………………………………
B58: Name of Tenderer: | G58: ……………………………………………………
B60: Date: | G60: ……………………………………………………
A63: [BLANK PAGE]

Sheet A1
A2: THE GOVERNMENT OF THE HONG KONG SPECIAL ADMINISTRATIVE REGION
A4: HIGHWAYS DEPARTMENT
A5: MAJOR WORKS PROJECT MANAGEMENT OFFICE
A7: ='Grand Summary'!A7:K7 -> CONTRACT NO. HY/2022/14
A8: ='Grand Summary'!A8:K8 -> MODIFICATION WORKS OF NOISE BARRIERS ALONG YUEN LONG HIGHWAY NEAR PARK SIGNATURE
A10: ACTIVITY SCHEDULE
A12: Schedule No. 1 - Preliminaries
A14: Item | B14: Activity | J14: Prices (HK$)
A16: 1.1 | B16: Temporary Accommodation for the Project Manager and Supervisor
A18: 1.1.1 | B18: Provision of the temporary accommodation for the Project Manager and Supervisor to the satisfaction of the Project Manager | J18: $
A21: 1.1.2 | B21: Provision of all furniture required by this contract to enable operation | J21: $
A23: 1.1.3.1 | B23: Fulfilling the obligations of maintenance of temporary accommodation provided for the 1st calendar month | J23: $
A24: 1.1.3.2 | B24: Fulfilling the obligations of maintenance of temporary accommodation provided for the 2nd calendar month | J24: $
A25: 1.1.3.3 | B25: Fulfilling the obligations of maintenance of temporary accommodation provided for the 3rd calendar month | J25: $
A26: 1.1.3.4 | B26: Fulfilling the obligations of maintenance of temporary accommodation provided for the 4th calendar month | J26: $
A27: 1.1.3.5 | B27: Fulfilling the obligations of maintenance of temporary accommodation provided for the 5th calendar month | J27: $
A28: 1.1.3.6 | B28: Fulfilling the obligations of maintenance of temporary accommodation provided for the 6th calendar month | J28: $
A29: 1.1.3.7 | B29: Fulfilling the obligations of maintenance of temporary accommodation provided for the 7th calendar month | J29: $
A30: 1.1.3.8 | B30: Fulfilling the obligations of maintenance of temporary accommodation provided for the 8th calendar month | J30: $
A31: 1.1.3.9 | B31: Fulfilling the obligations of maintenance of temporary accommodation provided for the 9th calendar month | J31: $
A32: 1.1.3.10 | B32: Fulfilling the obligations of maintenance of temporary accommodation provided for the 10th calendar month | J32: $
... A48: 1.1.4 | B48: Demolition, clear and reinstatement of the area occupied by temporary accommodation and handover to the Client | J48: $
I80: Total carried to collection | J80: $
A81: Item | B81: Activity | J81: Prices (HK$)
A83: 1.2 | B83: Temporary Accommodation for the Contractor
A85: 1.2.1 | B85: Provision of the temporary accommodation including workshops, offices, storage sheds and security system for the Contractor to the satisfaction of the Project Manager | J85: $
A88: 1.2.2 | B88: Provision of all furniture required by this contract to enable operation | J88: $
A90: 1.2.3.1 | B90: Fulfilling the obligations of servicing of the Contractor's temporary accommodation for the 1st calendar month | J90: $
A91: 1.2.3.2 | B91: Fulfilling the obligations of servicing of the Contractor's temporary accommodation for the 2nd calendar month | J91: $
A92: 1.2.3.3 | B92: Fulfilling the obligations of servicing of the Contractor's temporary accommodation for the 3rd calendar month | J92: $
A93: 1.2.3.4 | B93: Fulfilling the obligations of servicing of the Contractor's temporary accommodation for the 4th calendar month | J93: $
A94: 1.2.3.5 | B94: Fulfilling the obligations of servicing of the Contractor's temporary accommodation for the 5th calendar month | J94: $
A95: 1.2.3.6 | B95: Fulfilling the obligations of servicing of the Contractor's temporary accommodation for the 6th calendar month | J95: $
A96: 1.2.3.7 | B96: Fulfilling the obligations of servicing of the Contractor's temporary accommodation for the 7th calendar month | J96: $
A97: 1.2.3.8 | B97: Fulfilling the obligations of servicing of the Contractor's temporary accommodation for the 8th calendar month | J97: $
A98: 1.2.3.9 | B98: Fulfilling the obligations of servicing of the Contractor's temporary accommodation for the 9th calendar month | J98: $
A99: 1.2.3.10 | B99: Fulfilling the obligations of servicing of the Contractor's temporary accommodation for the 10th calendar month | J99: $
... A115: 1.2.4 | B115: Demolition, clear and reinstatement of the area occupied by temporary accommodation and handover to the Client | J115: $
I150: Total carried to collection | J150: $
A151: Item | B151: Activity | J151: Prices (HK$)
A153: 1.3 | B153: Computer Facilities for the Project Manager and Supervisor
A155: 1.3.1 | B155: Provision of computer facilities required by this contract to enable operation | J155: $
A157: 1.3.2.1 | B157: Fulfilling the obligations of maintenance and servicing of computer facilities for the 1st calendar month | J157: $
A158: 1.3.2.2 | B158: Fulfilling the obligations of maintenance and servicing of computer facilities for the 2nd calendar month | J158: $
A159: 1.3.2.3 | B159: Fulfilling the obligations of maintenance and servicing of computer facilities for the 3rd calendar month | J159: $
A160: 1.3.2.4 | B160: Fulfilling the obligations of maintenance and servicing of computer facilities for the 4th calendar month | J160: $
A161: 1.3.2.5 | B161: Fulfilling the obligations of maintenance and servicing of computer facilities for the 5th calendar month | J161: $
A162: 1.3.2.6 | B162: Fulfilling the obligations of maintenance and servicing of computer facilities for the 6th calendar month | J162: $
A163: 1.3.2.7 | B163: Fulfilling the obligations of maintenance and servicing of computer facilities for the 7th calendar month | J163: $
A164: 1.3.2.8 | B164: Fulfilling the obligations of maintenance and servicing of computer facilities for the 8th calendar month | J164: $
A165: 1.3.2.9 | B165: Fulfilling the obligations of maintenance and servicing of computer facilities for the 9th calendar month | J165: $
A166: 1.3.2.10 | B166: Fulfilling the obligations of maintenance and servicing of computer facilities for the 10th calendar month | J166: $
A167: 1.3.2.11 | B167: Fulfilling the obligations of maintenance and servicing of computer facilities for the 11th calendar month | J167: $
... A182: 1.3.3 | B182: Provision of required computer facilities training | J182: $
I220: Total carried to collection | J220: $
A221: Item | B221: Activity | J221: Prices (HK$)
A223: 1.4 | B223: Transport for the use of the Project Manager and Supervisor
A225: 1.4.1 | B225: Provision of land transport | J225: $
A227: 1.4.2.1 | B227: Fulfilling the obligations of maintenance of land transport provided for the 1st calendar month | J227: $
A228: 1.4.2.2 | B228: Fulfilling the obligations of maintenance of land transport provided for the 2nd calendar month | J228: $
A229: 1.4.2.3 | B229: Fulfilling the obligations of maintenance of land transport provided for the 3rd calendar month | J229: $
A230: 1.4.2.4 | B230: Fulfilling the obligations of maintenance of land transport provided for the 4th calendar month | J230: $
A231: 1.4.2.5 | B231: Fulfilling the obligations of maintenance of land transport provided for the 5th calendar month | J231: $
A232: 1.4.2.6 | B232: Fulfilling the obligations of maintenance of land transport provided for the 6th calendar month | J232: $
A233: 1.4.2.7 | B233: Fulfilling the obligations of maintenance of land transport provided for the 7th calendar month | J233: $
A234: 1.4.2.8 | B234: Fulfilling the obligations of maintenance of land transport provided for the 8th calendar month | J234: $
A235: 1.4.2.9 | B235: Fulfilling the obligations of maintenance of land transport provided for the 9th calendar month | J235: $
A236: 1.4.2.10 | B236: Fulfilling the obligations of maintenance of land transport provided for the 10th calendar month | J236: $
A237: 1.4.2.11 | B237: Fulfilling the obligations of maintenance of land transport provided for the 11th calendar month | J237: $
... A250: 1.4.2.24 | B250: Fulfilling the obligations of maintenance of land transport provided for the 24th calendar month | J250: $
I278: Total carried to collection | J278: $
A279: Item | B279: Activity | J279: Prices (HK$)
A281: 1.5 | B281: Mobile communication devices
A283: 1.5.1 | B283: Provision of the mobile communication devices | J283: $
A285: 1.5.2.1 | B285: Fulfilling the obligation of operation and maintenance of mobile communication devices for the 1st calendar month | J285: $
A286: 1.5.2.2 | B286: Fulfilling the obligation of operation and maintenance of mobile communication devices for the 2nd calendar month | J286: $
A287: 1.5.2.3 | B287: Fulfilling the obligation of operation and maintenance of mobile communication devices for the 3rd calendar month | J287: $
A288: 1.5.2.4 | B288: Fulfilling the obligation of operation and maintenance of mobile communication devices for the 4th calendar month | J288: $
A289: 1.5.2.5 | B289: Fulfilling the obligation of operation and maintenance of mobile communication devices for the 5th calendar month | J289: $
A290: 1.5.2.6 | B290: Fulfilling the obligation of operation and maintenance of mobile communication devices for the 6th calendar month | J290: $
A291: 1.5.2.7 | B291: Fulfilling the obligation of operation and maintenance of mobile communication devices for the 7th calendar month | J291: $
A292: 1.5.2.8 | B292: Fulfilling the obligation of operation and maintenance of mobile communication devices for the 8th calendar month | J292: $
A293: 1.5.2.9 | B293: Fulfilling the obligation of operation and maintenance of mobile communication devices for the 9th calendar month | J293: $
A294: 1.5.2.10 | B294: Fulfilling the obligation of operation and maintenance of mobile communication devices for the 10th calendar month | J294: $
A295: 1.5.2.11 | B295: Fulfilling the obligation of operation and maintenance of mobile communication devices for the 11th calendar month | J295: $
... A308: 1.5.2.24 | B308: Fulfilling the obligation of operation and maintenance of mobile communication devices for the 24th calendar month | J308: $
I336: Total carried to collection | J336: $
A337: Item | B337: Activity | J337: Prices (HK$)
A339: 1.6 | B339: Public Complaints and Enquiries cum Information Centre
A341: 1.6.1 | B341: Completion of provision of 24-hour telephone hotline to receive enquiries | J341: $
A343: 1.6.2.1 | B343: Fulfilling the obligations of maintenance of 24-hours telephone hotline system provided for the 1st calendar month | J343: $
A344: 1.6.2.2 | B344: Fulfilling the obligations of maintenance of 24-hours telephone hotline system provided for the 2nd calendar month | J344: $
A345: 1.6.2.3 | B345: Fulfilling the obligations of maintenance of 24-hours telephone hotline system provided for the 3rd calendar month | J345: $
A346: 1.6.2.4 | B346: Fulfilling the obligations of maintenance of 24-hours telephone hotline system provided for the 4th calendar month | J346: $
A347: 1.6.2.5 | B347: Fulfilling the obligations of maintenance of 24-hours telephone hotline system provided for the 5th calendar month | J347: $
A348: 1.6.2.6 | B348: Fulfilling the obligations of maintenance of 24-hours telephone hotline system provided for the 6th calendar month | J348: $
A349: 1.6.2.7 | B349: Fulfilling the obligations of maintenance of 24-hours telephone hotline system provided for the 7th calendar month | J349: $
A350: 1.6.2.8 | B350: Fulfilling the obligations of maintenance of 24-hours telephone hotline system provided for the 8th calendar month | J350: $
A351: 1.6.2.9 | B351: Fulfilling the obligations of maintenance of 24-hours telephone hotline system provided for the 9th calendar month | J351: $
A352: 1.6.2.10 | B352: Fulfilling the obligations of maintenance of 24-hours telephone hotline system provided for the 10th calendar month | J352: $
...

Sheet A2
A2: THE GOVERNMENT OF THE HONG KONG SPECIAL ADMINISTRATIVE REGION
A4: HIGHWAYS DEPARTMENT
A5: MAJOR WORKS PROJECT MANAGEMENT OFFICE
A7: ='Grand Summary'!A7:K7 -> CONTRACT NO. HY/2022/14
A8: ='Grand Summary'!A8:K8 -> MODIFICATION WORKS OF NOISE BARRIERS ALONG YUEN LONG HIGHWAY NEAR PARK SIGNATURE
A10: ACTIVITY SCHEDULE
A12: Schedule No. 2 - Preservation and Protection of Trees
A14: Item | B14: Activity | J14: Prices (HK$)
A16: 2 | B16: Preservation and Protection of Trees
A18: 2.1 | B18: Preservation and protection measures to the preserved trees
A20: 2.1.1 | B20: Fulfilling the obligations of preservation and protection measures to the preserved trees for the 1st calender month | J20: $
A21: 2.1.2 | B21: Fulfilling the obligations of preservation and protection measures to the preserved trees for the 2nd calender month | J21: $
A22: 2.1.3 | B22: Fulfilling the obligations of preservation and protection measures to the preserved trees for the 3rd calender month | J22: $
A23: 2.1.4 | B23: Fulfilling the obligations of preservation and protection measures to the preserved trees for the 4th calender month | J23: $
A24: 2.1.5 | B24: Fulfilling the obligations of preservation and protection measures to the preserved trees for the 5th calender month | J24: $
A25: 2.1.6 | B25: Fulfilling the obligations of preservation and protection measures to the preserved trees for the 6th calender month | J25: $
A26: 2.1.7 | B26: Fulfilling the obligations of preservation and protection measures to the preserved trees for the 7th calender month | J26: $
A27: 2.1.8 | B27: Fulfilling the obligations of preservation and protection measures to the preserved trees for the 8th calender month | J27: $
A28: 2.1.9 | B28: Fulfilling the obligations of preservation and protection measures to the preserved trees for the 9th calender month | J28: $
A29: 2.1.10 | B29: Fulfilling the obligations of preservation and protection measures to the preserved trees for the 10th calender month | J29: $
A30: 2.1.11 | B30: Fulfilling the obligations of preservation and protection measures to the preserved trees for the 11th calender month | J30: $
A31: 2.1.12 | B31: Fulfilling the obligations of preservation and protection measures to the preserved trees for the 12th calender month | J31: $
... A43: 2.1.24 | B43: Fulfilling the obligations of preservation and protection measures to the preserved trees for the 24th calender month | J43: $
A45: 2.2 | B45: Tree survey of existing trees and Report on updating of photographical records | J45: $
A47: 2.3 | B47: Tree risk assessment | J47: $
A49: 2.4 | B49: Additional items required by the Contractor (to be inserted by the Contractor) | J49: $
I71: Total Prices of Schedule No. 2 Carried to Grand Summary of the Activity Schedule | J71: $
A72: Item | B72: Activity | J72: Prices (HK$)
B74: Collection from Page AS.S4/1 | J74: $
I133: Total Prices of Schedule No. 4 Carried to Grand Summary of the Activity Schedule | J133: $

Sheet A3
A2: THE GOVERNMENT OF THE HONG KONG SPECIAL ADMINISTRATIVE REGION
A4: HIGHWAYS DEPARTMENT
A5: MAJOR WORKS PROJECT MANAGEMENT OFFICE
A7: ='Grand Summary'!A7:K7 -> CONTRACT NO. HY/2022/14
A8: ='Grand Summary'!A8:K8 -> MODIFICATION WORKS OF NOISE BARRIERS ALONG YUEN LONG HIGHWAY NEAR PARK SIGNATURE
A10: ACTIVITY SCHEDULE
A12: Schedule No. 3 - Modification Works of Noise Barriers
A14: Item | B14: Activity | J14: Prices (HK$)
A16: 3 | B16: Modification Works of Noise Barriers
A18: 3.1 | B18: Dismantling and disposal of existing steel posts, sub-frames, base plates and other accessories of noise barriers
A20: 3.1.1 | B20: Completion of dismantling and disposal of existing vertical posts, sub-frames, base plates and other accessories | J20: $
B21: of noise barriers for Bay A1
A22: 3.1.2 | B22: Completion of dismantling and disposal of existing vertical posts, sub-frames, base plates and other accessories | J22: $
B23: of noise barriers for Bay B1
A24: 3.1.3 | B24: Completion of dismantling and disposal of existing vertical posts, sub-frames, base plates and other accessories | J24: $
B25: of noise barriers for Bay B2
A26: 3.1.4 | B26: Completion of dismantling and disposal of existing vertical posts, sub-frames, base plates and other accessories | J26: $
B27: of noise barriers for Bay B3
A28: 3.1.5 | B28: Completion of dismantling and disposal of existing vertical posts, sub-frames, base plates and other accessories | J28: $
B29: of noise barriers for Bay B4
A30: 3.1.6 | B30: Completion of dismantling and disposal of existing vertical posts, sub-frames, base plates and other accessories | J30: $
B31: of noise barriers for Bay B5
A32: 3.1.7 | B32: Completion of dismantling and disposal of existing vertical posts, sub-frames, base plates and other accessories | J32: $
B33: of noise barriers for Bay C1
A34: 3.1.8 | B34: Completion of dismantling and disposal of existing vertical posts, sub-frames, base plates and other accessories | J34: $
B35: of noise barriers for Bay C2
A36: 3.1.9 | B36: Completion of dismantling and disposal of existing vertical posts, sub-frames, base plates and other accessories | J36: $
B37: of noise barriers for Bay C3
A38: 3.1.10 | B38: Completion of dismantling and disposal of existing vertical posts, sub-frames, base plates and other accessories | J38: $
B39: of noise barriers for Bay C4
A40: 3.1.11 | B40: Completion of dismantling and disposal of existing vertical posts, sub-frames, base plates and other accessories | J40: $
B41: of noise barriers for Bay C5
A43: 3.2 | B43: Installation of new vertical posts and base plates of noise barriers
A45: 3.2.1 | B45: Completion of installation of new vertical posts and base plates of noise barriers for Bay A1 | J45: $
A46: 3.2.2 | B46: Completion of installation of new vertical posts and base plates of noise barriers for Bay B1 | J46: $
A47: 3.2.3 | B47: Completion of installation of new vertical posts and base plates of noise barriers for Bay B2 | J47: $
A48: 3.2.4 | B48: Completion of installation of new vertical posts and base plates of noise barriers for Bay B3 | J48: $
A49: 3.2.5 | B49: Completion of installation of new vertical posts and base plates of noise barriers for Bay B4 | J49: $
A50: 3.2.6 | B50: Completion of installation of new vertical posts and base plates of noise barriers for Bay B5 | J50: $
A51: 3.2.7 | B51: Completion of installation of new vertical posts and base plates of noise barriers for Bay C1 | J51: $
A52: 3.2.8 | B52: Completion of installation of new vertical posts and base plates of noise barriers for Bay C2 | J52: $
A53: 3.2.9 | B53: Completion of installation of new vertical posts and base plates of noise barriers for Bay C3 | J53: $
A54: 3.2.10 | B54: Completion of installation of new vertical posts and base plates of noise barriers for Bay C4 | J54: $
A55: 3.2.11 | B55: Completion of installation of new vertical posts and base plates of noise barriers for Bay C5 | J55: $
I70: Total carried to collection | J70: $
A71: Item | B71: Activity | J71: Prices (HK$)
A73: 3.3 | B73: Dismantling, storing and re-erecting of existing noise barrier panels
A75: 3.3.1 | B75: Completion of dismantling, storing and re-erecting of existing noise barrier panels for Bay A1 | J75: $
A76: 3.3.2 | B76: Completion of dismantling, storing and re-erecting of existing noise barrier panels for Bay B1 | J76: $
A77: 3.3.3 | B77: Completion of dismantling, storing and re-erecting of existing noise barrier panels for Bay B2 | J77: $
A78: 3.3.4 | B78: Completion of dismantling, storing and re-erecting of existing noise barrier panels for Bay B3 | J78: $
A79: 3.3.5 | B79: Completion of dismantling, storing and re-erecting of existing noise barrier panels for Bay B4 | J79: $
A80: 3.3.6 | B80: Completion of dismantling, storing and re-erecting of existing noise barrier panels for Bay B5 | J80: $
A81: 3.3.7 | B81: Completion of dismantling, storing and re-erecting of existing noise barrier panels for Bay C1 | J81: $
A82: 3.3.8 | B82: Completion of dismantling, storing and re-erecting of existing noise barrier panels for Bay C2 | J82: $
A83: 3.3.9 | B83: Completion of dismantling, storing and re-erecting of existing noise barrier panels for Bay C3 | J83: $
A84: 3.3.10 | B84: Completion of dismantling, storing and re-erecting of existing noise barrier panels for Bay C4 | J84: $
A85: 3.3.11 | B85: Completion of dismantling, storing and re-erecting of existing noise barrier panels for Bay C5 | J85: $
A87: 3.4 | B87: Installation of new sub-frames and other accessories of noise barriers
A89: 3.4.1 | B89: Completion of installation of new sub-frames and other accessories of noise barriers for Bay A1 | J89: $
A90: 3.4.2 | B90: Completion of installation of new sub-frames and other accessories of noise barriers for Bay B1 | J90: $
A91: 3.4.3 | B91: Completion of installation of new sub-frames and other accessories of noise barriers for Bay B2 | J91: $
A92: 3.4.4 | B92: Completion of installation of new sub-frames and other accessories of noise barriers for Bay B3 | J92: $
A93: 3.4.5 | B93: Completion of installation of new sub-frames and other accessories of noise barriers for Bay B4 | J93: $
A94: 3.4.6 | B94: Completion of installation of new sub-frames and other accessories of noise barriers for Bay B5 | J94: $
A95: 3.4.7 | B95: Completion of installation of new sub-frames and other accessories of noise barriers for Bay C1 | J95: $
A96: 3.4.8 | B96: Completion of installation of new sub-frames and other accessories of noise barriers for Bay C2 | J96: $
A97: 3.4.9 | B97: Completion of installation of new sub-frames and other accessories of noise barriers for Bay C3 | J97: $
A98: 3.4.10 | B98: Completion of installation of new sub-frames and other accessories of noise barriers for Bay C4 | J98: $
A99: 3.4.11 | B99: Completion of installation of new sub-frames and other accessories of noise barriers for Bay C5 | J99: $
I128: Total carried to collection | J128: $
A129: Item | B129: Activity | J129: Prices (HK$)
A131: 3.5 | B131: Installation of new panels of noise barriers
A133: 3.5.1 | B133: Completion of installation of new panels of noise barriers for Bay A1 | J133: $
A134: 3.5.2 | B134: Completion of installation of new panels of noise barriers for Bay B1 | J134: $
A135: 3.5.3 | B135: Completion of installation of new panels of noise barriers for Bay B2 | J135: $
A136: 3.5.4 | B136: Completion of installation of new panels of noise barriers for Bay B3 | J136: $
A137: 3.5.5 | B137: Completion of installation of new panels of noise barriers for Bay B4 | J137: $
A138: 3.5.6 | B138: Completion of installation of new panels of noise barriers for Bay B5 | J138: $
A139: 3.5.7 | B139: Completion of installation of new panels of noise barriers for Bay C1 | J139: $
A140: 3.5.8 | B140: Completion of installation of new panels of noise barriers for Bay C2 | J140: $
A141: 3.5.9 | B141: Completion of installation of new panels of noise barriers for Bay C3 | J141: $
A142: 3.5.10 | B142: Completion of installation of new panels of noise barriers for Bay C4 | J142: $
A143: 3.5.11 | B143: Completion of installation of new panels of noise barriers for Bay C5 | J143: $
I186: Total carried to collection | J186: $
A187: Item | B187: Activity | J187: Prices (HK$)
A189: 3.6 | B189: Contractor's Design for Noise Barriers Bay A1, Bay B1 to B5 and Bay C1 to C5
A191: 3.6.1 | B191: Submission of Contractor's Design and Check Certificates on noise barrier panels, sub-frames and other accessories | J191: $
B192: for the full compliance with Specification and Drawings of the Contract with Project Manager's approval
A194: 3.7 | B194: Spare Parts
A196: 3.7.1 | B196: Provision of additional PMMA panels as specified in PS Clause 27.19 | J196: $
A197: 3.7.2 | B197: Provision of additional polycarbonate panels as specified in PS Clause 27.19 | J197: $
A198: 3.7.3 | B198: Provision of additional stainless steel hexagon nuts with washers as specified in PS Clause 27.19 | J198: $
A200: 3.8 | B200: Miscellanous
A202: 3.8.1 | B202: Submission of As-constructed Drawings | J202: $
A204: 3.8.2 | B204: Submission of Operation and Maintenance Manuals | J204: $
A206: 3.9 | B206: Additional items required by the Contractor (to be inserted by the Contractor) | J206: $
I242: Total carried to collection | J242: $
A243: Item | B243: Activity | J243: Prices (HK$)
B245: Collection from Page AS.S3/1 | J245: $
...

Sheet A4
A2: THE GOVERNMENT OF THE HONG KONG SPECIAL ADMINISTRATIVE REGION
A4: HIGHWAYS DEPARTMENT
A5: MAJOR WORKS PROJECT MANAGEMENT OFFICE
A7: ='Grand Summary'!A7:K7 -> CONTRACT NO. HY/2022/14
A8: ='Grand Summary'!A8:K8 -> MODIFICATION WORKS OF NOISE BARRIERS ALONG YUEN LONG HIGHWAY NEAR PARK SIGNATURE
A10: ACTIVITY SCHEDULE
A12: Schedule No. 4 - Monitoring Payment of Wages
A14: Item | B14: Activity | J14: Prices (HK$)
A16: 4 | B16: Monitoring Payment of Wages
A18: 4.1 | B18: Completion of establishment monitoring system for payment of wages | J18: $
A20: 4.2.1 | B20: Fulfilling the obligations of operating the monitoring system of payment of wages for the 1st calendar month | J20: $ | K20: 9000
A21: 4.2.2 | B21: Fulfilling the obligations of operating the monitoring system of payment of wages for the 2nd calendar month | J21: $ | K21: 9000
A22: 4.2.3 | B22: Fulfilling the obligations of operating the monitoring system of payment of wages for the 3rd calendar month | J22: $ | K22: 9000
A23: 4.2.4 | B23: Fulfilling the obligations of operating the monitoring system of payment of wages for the 4th calendar month | J23: $ | K23: 9000
A24: 4.2.5 | B24: Fulfilling the obligations of operating the monitoring system of payment of wages for the 5th calendar month | J24: $ | K24: 9000
A25: 4.2.6 | B25: Fulfilling the obligations of operating the monitoring system of payment of wages for the 6th calendar month | J25: $ | K25: 9000
A26: 4.2.7 | B26: Fulfilling the obligations of operating the monitoring system of payment of wages for the 7th calendar month | J26: $ | K26: 9000
A27: 4.2.8 | B27: Fulfilling the obligations of operating the monitoring system of payment of wages for the 8th calendar month | J27: $ | K27: 9000
A28: 4.2.9 | B28: Fulfilling the obligations of operating the monitoring system of payment of wages for the 9th calendar month | J28: $ | K28: 9000
A29: 4.2.10 | B29: Fulfilling the obligations of operating the monitoring system of payment of wages for the 10th calendar month | J29: $ | K29: 9000
A30: 4.2.11 | B30: Fulfilling the obligations of operating the monitoring system of payment of wages for the 11th calendar month | J30: $ | K30: 9000
A31: 4.2.12 | B31: Fulfilling the obligations of operating the monitoring system of payment of wages for the 12th calendar month | J31: $ | K31: 9000
... A43: 4.2.24 | B43: Fulfilling the obligations of operating the monitoring system of payment of wages for the 24th calendar month | J43: $ | K43: 9000
I71: Total carried to collection | J71: $
A72: Item | B72: Activity | J72: Prices (HK$)
A74: 4.3 | B74: Contractor's Labour Officer
A76: 4.3.1 | B76: Provision of Contractor's Labour Officer for the 1st calendar month | J76: $
A77: 4.3.2 | B77: Provision of Contractor's Labour Officer for the 2nd calendar month | J77: $
A78: 4.3.3 | B78: Provision of Contractor's Labour Officer for the 3rd calendar month | J78: $
A79: 4.3.4 | B79: Provision of Contractor's Labour Officer for the 4th calendar month | J79: $
A80: 4.3.5 | B80: Provision of Contractor's Labour Officer for the 5th calendar month | J80: $
A81: 4.3.6 | B81: Provision of Contractor's Labour Officer for the 6th calendar month | J81: $
A82: 4.3.7 | B82: Provision of Contractor's Labour Officer for the 7th calendar month | J82: $
A83: 4.3.8 | B83: Provision of Contractor's Labour Officer for the 8th calendar month | J83: $
A84: 4.3.9 | B84: Provision of Contractor's Labour Officer for the 9th calendar month | J84: $
A85: 4.3.10 | B85: Provision of Contractor's Labour Officer for the 10th calendar month | J85: $
A86: 4.3.11 | B86: Provision of Contractor's Labour Officer for the 11th calendar month | J86: $
A87: 4.3.12 | B87: Provision of Contractor's Labour Officer for the 12th calendar month | J87: $
... A99: 4.3.24 | B99: Provision of Contractor's Labour Officer for the 24th calendar month | J99: $
I129: Total carried to collection | J129: $
A130: Item | B130: Activity | J130: Prices (HK$)
B132: Collection from Page AS.S4/1 | J132: $
B133: Collection from Page AS.S4/2 | J133: $
I187: Total Prices of Schedule No. 4 Carried to Grand Summary of the Activity Schedule | J187: $

Sheet A5
A2: THE GOVERNMENT OF THE HONG KONG SPECIAL ADMINISTRATIVE REGION
A4: HIGHWAYS DEPARTMENT
A5: MAJOR WORKS PROJECT MANAGEMENT OFFICE
A7: ='Grand Summary'!A7:K7 -> CONTRACT NO. HY/2022/14
A8: ='Grand Summary'!A8:K8 -> MODIFICATION WORKS OF NOISE BARRIERS ALONG YUEN LONG HIGHWAY NEAR PARK SIGNATURE
A10: ACTIVITY SCHEDULE
A12: Schedule No. 5 - Site Safety
A14: Item | B14: Activity | J14: Prices (HK$)
A16: 5 | B16: Site Safety
A18: 5.1.1 | B18: Provide Safety Officer for the 1st calendar month | J18: $ | K18: 1800
A19: 5.1.2 | B19: Provide Safety Officer for the 2nd calendar month | J19: $ | K19: 1800
A20: 5.1.3 | B20: Provide Safety Officer for the 3rd calendar month | J20: $ | K20: 1800
A21: 5.1.4 | B21: Provide Safety Officer for the 4th calendar month | J21: $ | K21: 1800
A22: 5.1.5 | B22: Provide Safety Officer for the 5th calendar month | J22: $ | K22: 1800
A23: 5.1.6 | B23: Provide Safety Officer for the 6th calendar month | J23: $ | K23: 1800
A24: 5.1.7 | B24: Provide Safety Officer for the 7th calendar month | J24: $ | K24: 1800
A25: 5.1.8 | B25: Provide Safety Officer for the 8th calendar month | J25: $ | K25: 1800
A26: 5.1.9 | B26: Provide Safety Officer for the 9th calendar month | J26: $ | K26: 1800
A27: 5.1.10 | B27: Provide Safety Officer for the 10th calendar month | J27: $ | K27: 1800
A28: 5.1.11 | B28: Provide Safety Officer for the 11th calendar month | J28: $ | K28: 1800
A29: 5.1.12 | B29: Provide Safety Officer for the 12th calendar month | J29: $ | K29: 1800
... A41: 5.1.24 | B41: Provide Safety Officer for the 24th calendar month | J41: $ | K41: 1800
I72: Total carried to collection | J72: $ | K72: =SUM(K18:K70) -> 43200
A73: Item | B73: Activity | J73: Prices (HK$)
A75: 5.2.1 | B75: Attend Site Safety Meeting Committee for the 1st calendar month | J75: $ | K75: 445
A76: 5.2.2 | B76: Attend Site Safety Meeting Committee for the 2nd calendar month | J76: $ | K76: 445
A77: 5.2.3 | B77: Attend Site Safety Meeting Committee for the 3rd calendar month | J77: $ | K77: 445
A78: 5.2.4 | B78: Attend Site Safety Meeting Committee for the 4th calendar month | J78: $ | K78: 445
A79: 5.2.5 | B79: Attend Site Safety Meeting Committee for the 5th calendar month | J79: $ | K79: 445
A80: 5.2.6 | B80: Attend Site Safety Meeting Committee for the 6th calendar month | J80: $ | K80: 445
A81: 5.2.7 | B81: Attend Site Safety Meeting Committee for the 7th calendar month | J81: $ | K81: 445
A82: 5.2.8 | B82: Attend Site Safety Meeting Committee for the 8th calendar month | J82: $ | K82: 445
A83: 5.2.9 | B83: Attend Site Safety Meeting Committee for the 9th calendar month | J83: $ | K83: 445
A84: 5.2.10 | B84: Attend Site Safety Meeting Committee for the 10th calendar month | J84: $ | K84: 445
A85: 5.2.11 | B85: Attend Site Safety Meeting Committee for the 11th calendar month | J85: $ | K85: 445
A86: 5.2.12 | B86: Attend Site Safety Meeting Committee for the 12th calendar month | J86: $ | K86: 445
... A98: 5.2.24 | B98: Attend Site Safety Meeting Committee for the 24th calendar month | J98: $ | K98: 445
I135: Total carried to collection | J135: $ | K135: =SUM(K75:K133) -> 10680
A136: Item | B136: Activity | J136: Prices (HK$)
A138: 5.3.1 | B138: Attend Site Safety Committee for the 1st calendar month | J138: $ | K138: 445
A139: 5.3.2 | B139: Attend Site Safety Committee for the 2nd calendar month | J139: $ | K139: 445
A140: 5.3.3 | B140: Attend Site Safety Committee for the 3rd calendar month | J140: $ | K140: 445
A141: 5.3.4 | B141: Attend Site Safety Committee for the 4th calendar month | J141: $ | K141: 445
A142: 5.3.5 | B142: Attend Site Safety Committee for the 5th calendar month | J142: $ | K142: 445
A143: 5.3.6 | B143: Attend Site Safety Committee for the 6th calendar month | J143: $ | K143: 445
A144: 5.3.7 | B144: Attend Site Safety Committee for the 7th calendar month | J144: $ | K144: 445
A145: 5.3.8 | B145: Attend Site Safety Committee for the 8th calendar month | J145: $ | K145: 445
A146: 5.3.9 | B146: Attend Site Safety Committee for the 9th calendar month | J146: $ | K146: 445
A147: 5.3.10 | B147: Attend Site Safety Committee for the 10th calendar month | J147: $ | K147: 445
A148: 5.3.11 | B148: Attend Site Safety Committee for the 11th calendar month | J148: $ | K148: 445
A149: 5.3.12 | B149: Attend Site Safety Committee for the 12th calendar month | J149: $ | K149: 445
... A161: 5.3.24 | B161: Attend Site Safety Committee for the 24th calendar month | J161: $ | K161: 445
I198: Total carried to collection | J198: $ | K198: =SUM(K138:K196) -> 10680
A199: Item | B199: Activity | J199: Prices (HK$)
A201: 5.4.1 | B201: Arrange and attend weekly safety walk for the 1st calendar month | J201: $ | K201: 1340
A202: 5.4.2 | B202: Arrange and attend weekly safety walk for the 2nd calendar month | J202: $ | K202: 1340
A203: 5.4.3 | B203: Arrange and attend weekly safety walk for the 3rd calendar month | J203: $ | K203: 1340
A204: 5.4.4 | B204: Arrange and attend weekly safety walk for the 4th calendar month | J204: $ | K204: 1340
A205: 5.4.5 | B205: Arrange and attend weekly safety walk for the 5th calendar month | J205: $ | K205: 1340
A206: 5.4.6 | B206: Arrange and attend weekly safety walk for the 6th calendar month | J206: $ | K206: 1340
A207: 5.4.7 | B207: Arrange and attend weekly safety walk for the 7th calendar month | J207: $ | K207: 1340
A208: 5.4.8 | B208: Arrange and attend weekly safety walk for the 8th calendar month | J208: $ | K208: 1340
A209: 5.4.9 | B209: Arrange and attend weekly safety walk for the 9th calendar month | J209: $ | K209: 1340
A210: 5.4.10 | B210: Arrange and attend weekly safety walk for the 10th calendar month | J210: $ | K210: 1340
A211: 5.4.11 | B211: Arrange and attend weekly safety walk for the 11th calendar month | J211: $ | K211: 1340
A212: 5.4.12 | B212: Arrange and attend weekly safety walk for the 12th calendar month | J212: $ | K212: 1340
... A224: 5.4.24 | B224: Arrange and attend weekly safety walk for the 24th calendar month | J224: $ | K224: 1340
I261: Total carried to collection | J261: $ | K261: =SUM(K201:K259) -> 32160
A262: Item | B262: Activity | J262: Prices (HK$)
A264: 5.5 | B264: Provide safety training in the form of safety training for specified trade workers
A265: 5.5.1.1 | B265: 1st One day course | J265: $ | K265: 600
A266: 5.5.1.2 | B266: 2nd One day course | J266: $ | K266: 600
A267: 5.5.1.3 | B267: 3rd One day course | J267: $ | K267: 600
A268: 5.5.1.4 | B268: 4th One day course | J268: $ | K268: 600
A269: 5.5.1.5 | B269: 5th One day course | J269: $ | K269: 600
A270: 5.5.1.6 | B270: 6th One day course | J270: $ | K270: 600
A271: 5.5.1.7 | B271: 7th One day course | J271: $ | K271: 600
A272: 5.5.1.8 | B272: 8th One day course | J272: $ | K272: 600
A273: 5.5.1.9 | B273: 9th One day course | J273: $ | K273: 600
A274: 5.5.1.10 | B274: 10th One day course | J274: $ | K274: 600
A275: 5.5.1.11 | B275: 11th One day course | J275: $ | K275: 600
A276: 5.5.1.12 | B276: 12th One day course | J276: $ | K276: 600
... A301: 5.5.2.18 | B301: 18th Half day validation course | J301: $ | K301: 350
I322: Total carried to collection | K322: =SUM(K265:K317) -> 17100
A325: 5.6.1 | B325: Provide safety training in the form of site specific induction training for the 1st calendar month | J325: $ | K325: 450
A326: 5.6.2 | B326: Provide safety training in the form of site specific induction training for the 2nd calendar month | J326: $ | K326: 450
A327: 5.6.3 | B327: Provide safety training in the form of site specific induction training for the 3rd calendar month | J327: $ | K327: 450
A328: 5.6.4 | B328: Provide safety training in the form of site specific induction training for the 4th calendar month | J328: $ | K328: 450
A329: 5.6.5 | B329: Provide safety training in the form of site specific induction training for the 5th calendar month | J329: $ | K329: 450
A330: 5.6.6 | B330: Provide safety training in the form of site specific induction training for the 6th calendar month | J330: $ | K330: 450
A331: 5.6.7 | B331: Provide safety training in the form of site specific induction training for the 7th calendar month | J331: $ | K331: 450
A332: 5.6.8 | B332: Provide safety training in the form of site specific induction training for the 8th calendar month | J332: $ | K332: 450
A333: 5.6.9 | B333: Provide safety training in the form of site specific induction training for the 9th calendar month | J333: $ | K333: 450
A334: 5.6.10 | B334: Provide safety training in the form of site specific induction training for the 10th calendar month | J334: $ | K334: 450
A335: 5.6.11 | B335: Provide safety training in the form of site specific induction training for the 11th calendar month | J335: $ | K335: 450
A336: 5.6.12 | B336: Provide safety training in the form of site specific induction training for the 12th calendar month | J336: $ | K336: 450
... A348: 5.6.24 | B348: Provide safety training in the form of site specific induction training for the 24th calendar month | J348: $ | K348: 450
I380: Total carried to collection | J380: $ | K380: =SUM(K325:K376) -> 10800
A381: Item | B381: Activity | J381: Prices (HK$)
A383: 5.7.1 | B383: Provide safety training in the form of tool-box talks for the 1st calendar month | J383: $ | K383: 900
...

Sheet A6
A2: THE GOVERNMENT OF THE HONG KONG SPECIAL ADMINISTRATIVE REGION
A4: HIGHWAYS DEPARTMENT
A5: MAJOR WORKS PROJECT MANAGEMENT OFFICE
A7: ='Grand Summary'!A7:K7 -> CONTRACT NO. HY/2022/14
A8: ='Grand Summary'!A8:K8 -> MODIFICATION WORKS OF NOISE BARRIERS ALONG YUEN LONG HIGHWAY NEAR PARK SIGNATURE
A10: ACTIVITY SCHEDULE
A12: Schedule No. 6 - Site Cleanliness and Tidiness
A14: Item | B14: Activity | J14: Prices (HK$)
A16: 6 | B16: Site Cleanliness and Tidiness
A18: 6.1.1 | B18: Completion of daily cleaning for the 1st calendar month | J18: $ | K18: 20333
A19: 6.1.2 | B19: Completion of daily cleaning for the 2nd calendar month | J19: $ | K19: 20333
A20: 6.1.3 | B20: Completion of daily cleaning for the 3rd calendar month | J20: $ | K20: 20333
A21: 6.1.4 | B21: Completion of daily cleaning for the 4th calendar month | J21: $ | K21: 20333
A22: 6.1.5 | B22: Completion of daily cleaning for the 5th calendar month | J22: $ | K22: 20333
A23: 6.1.6 | B23: Completion of daily cleaning for the 6th calendar month | J23: $ | K23: 20333
A24: 6.1.7 | B24: Completion of daily cleaning for the 7th calendar month | J24: $ | K24: 20333
A25: 6.1.8 | B25: Completion of daily cleaning for the 8th calendar month | J25: $ | K25: 20333
A26: 6.1.9 | B26: Completion of daily cleaning for the 9th calendar month | J26: $ | K26: 20333
A27: 6.1.10 | B27: Completion of daily cleaning for the 10th calendar month | J27: $ | K27: 20333
A28: 6.1.11 | B28: Completion of daily cleaning for the 11th calendar month | J28: $ | K28: 20333
A29: 6.1.12 | B29: Completion of daily cleaning for the 12th calendar month | J29: $ | K29: 20333
... A34: 6.1.17 | B34: Completion of daily cleaning for the 17th-24th calendar months | J34: $ | K34: 20333
I76: Total carried to collection | J76: $ | K76: =SUM(K18:K75) -> 345661
A77: Item | B77: Activity | J77: Prices (HK$)
A79: 6.2.1 | B79: Completion of weekly tidying for the 1st calendar month | J79: $ | K79: 4333
A80: 6.2.2 | B80: Completion of weekly tidying for the 2nd calendar month | J80: $ | K80: 4333
A81: 6.2.3 | B81: Completion of weekly tidying for the 3rd calendar month | J81: $ | K81: 4333
A82: 6.2.4 | B82: Completion of weekly tidying for the 4th calendar month | J82: $ | K82: 4333
A83: 6.2.5 | B83: Completion of weekly tidying for the 5th calendar month | J83: $ | K83: 4333
A84: 6.2.6 | B84: Completion of weekly tidying for the 6th calendar month | J84: $ | K84: 4333
A85: 6.2.7 | B85: Completion of weekly tidying for the 7th calendar month | J85: $ | K85: 4333
A86: 6.2.8 | B86: Completion of weekly tidying for the 8th calendar month | J86: $ | K86: 4333
A87: 6.2.9 | B87: Completion of weekly tidying for the 9th calendar month | J87: $ | K87: 4333
A88: 6.2.10 | B88: Completion of weekly tidying for the 10th calendar month | J88: $ | K88: 4333
A89: 6.2.11 | B89: Completion of weekly tidying for the 11th calendar month | J89: $ | K89: 4333
A90: 6.2.12 | B90: Completion of weekly tidying for the 12th calendar month | J90: $ | K90: 4333
... A95: 6.2.17 | B95: Completion of weekly tidying for the 17th-24th calendar months | J95: $ | K95: 4333
I140: Total carried to collection | J140: $ | K140: =SUM(K79:K139) -> 73661
A141: Item | B141: Activity | J141: Prices (HK$)
B143: Collection from Page AS.S6/1 | J143: $ | K143: =K76 -> 345661
B144: Collection from Page AS.S6/2 | J144: $ | K144: =K140 -> 73661
I204: Total Prices of Schedule No. 6 Carried to Grand Summary of the Activity Schedule | J204: $ | K204: =SUM(K143:K203) -> 419322

Sheet A13
A2: THE GOVERNMENT OF THE HONG KONG SPECIAL ADMINISTRATIVE REGION
A4: HIGHWAYS DEPARTMENT
A5: MAJOR WORKS PROJECT MANAGEMENT OFFICE
A7: CONTRACT NO. HY/2021/06
A8: RETROFITTING OF NOISE BARRIERS ON PO LAM ROAD NORTH AND PO NING ROAD
A10: ACTIVITY SCHEDULE
A12: Schedule No. 13 - Noise Barriers NB09
A14: Item | B14: Activity | J14: Prices (HK$)
A16: 13 | B16: Noise Barriers NB09
A18: 13.1 | B18: Piling Works
A20: 13.1.1 | B20: Establishment of piling plant | J20: $
A22: 13.1.2 | B22: Pre-drilling works | J22: $
A24: 13.1.3 | B24: Piling
A26: 13.1.3.1 | B26: Excavation of piles
A28: 13.1.3.1.1 | B28: Completion of excavation of piles for Bay NB09-01P | J28: $
A29: 13.1.3.1.2 | B29: Completion of excavation of piles for Bay NB09-02P | J29: $
A30: 13.1.3.1.3 | B30: Completion of excavation of piles for Bay NB09-03P | J30: $
A31: 13.1.3.1.4 | B31: Completion of excavation of piles for Bay NB09-04P | J31: $
A34: 13.1.3.2 | B34: Installation of reinforcement for piles
A36: 13.1.3.2.1 | B36: Completion of installation of reinforcement of piles for Bay NB09-01P | J36: $
A37: 13.1.3.2.2 | B37: Completion of installation of reinforcement of piles for Bay NB09-02P | J37: $
A38: 13.1.3.2.3 | B38: Completion of installation of reinforcement of piles for Bay NB09-03P | J38: $
A39: 13.1.3.2.4 | B39: Completion of installation of reinforcement of piles for Bay NB09-04P | J39: $
A42: 13.1.3.3 | B42: Completion of piling works
A44: 13.1.3.3.1 | B44: Completion of all piling works for Bay NB09-01P | J44: $
A45: 13.1.3.3.2 | B45: Completion of all piling works for Bay NB09-02P | J45: $
A46: 13.1.3.3.3 | B46: Completion of all piling works for Bay NB09-03P | J46: $
A47: 13.1.3.3.4 | B47: Completion of all piling works for Bay NB09-04P | J47: $
A50: 13.1.4 | B50: Pile tests
A52: 13.1.4.1 | B52: Completion of all pile tests | J52: $
I76: Total carried to collection | J76: $
A77: Item | B77: Activity | J77: Prices (HK$)
A79: 13.2 | B79: Substructure
A81: 13.2.1 | B81: Excavation for pile cap
A83: 13.2.1.1 | B83: Completion of excavation of pile cap for Bay NB09-01P | J83: $
A84: 13.2.1.2 | B84: Completion of excavation of pile cap for Bay NB09-02P | J84: $
A85: 13.2.1.3 | B85: Completion of excavation of pile cap for Bay NB09-03P | J85: $
A86: 13.2.1.4 | B86: Completion of excavation of pile cap for Bay NB09-04P | J86: $
A89: 13.2.2 | B89: Fixing of reinforcement
A91: 13.2.2.1 | B91: Completion of fixing of reinforcement of pile cap and stem wall for Bay NB09-01P | J91: $
A92: 13.2.2.2 | B92: Completion of fixing of reinforcement of pile cap and stem wall for Bay NB09-02P | J92: $
A93: 13.2.2.3 | B93: Completion of fixing of reinforcement of pile cap and stem wall for Bay NB09-03P | J93: $
A94: 13.2.2.4 | B94: Completion of fixing of reinforcement of pile cap and stem wall for Bay NB09-04P | J94: $
A97: 13.2.3 | B97: Completion of pile caps with stem wall
A99: 13.2.3.1 | B99: Completion of all pile caps with stem wall and movement joints for Bay NB09-01P | J99: $
A100: 13.2.3.2 | B100: Completion of all pile caps with stem wall and movement joints for Bay NB09-02P | J100: $
A101: 13.2.3.3 | B101: Completion of all pile caps with stem wall and movement joints for Bay NB09-03P | J101: $
A102: 13.2.3.4 | B102: Completion of all pile caps with stem wall and movement joints for Bay NB09-04P | J102: $
I138: Total carried to collection | J138: $
A139: Item | B139: Activity | J139: Prices (HK$)
A141: 13.3 | B141: Superstructure
A143: 13.3.1 | B143: Installation of vertical posts for noise barriers
A145: 13.3.1.1 | B145: Completion of installation of vertical posts of noise barriers for Bay NB09-01P | J145: $
A146: 13.3.1.2 | B146: Completion of installation of vertical posts of noise barriers for Bay NB09-02P | J146: $
A147: 13.3.1.3 | B147: Completion of installation of vertical posts of noise barriers for Bay NB09-03P | J147: $
A148: 13.3.1.4 | B148: Completion of installation of vertical posts of noise barriers for Bay NB09-04P | J148: $
A150: 13.3.2 | B150: Installation of tie beams for noise barriers
A152: 13.3.2.1 | B152: Completion of installation of tie bems of noise barriers for Bay NB09-01P | J152: $
A153: 13.3.2.2 | B153: Completion of installation of tie bems of noise barriers for Bay NB09-02P | J153: $
A154: 13.3.2.3 | B154: Completion of installation of tie bems of noise barriers for Bay NB09-03P | J154: $
A155: 13.3.2.4 | B155: Completion of installation of tie bems of noise barriers for Bay NB09-04P | J155: $
I203: Total carried to collection | J203: $
A204: Item | B204: Activity | J204: Prices (HK$)
A206: 13.4 | B206: Contractor's Design
B208: Tenderer is required to complete a detailed Schedule of Rates in accordance with ACC Clause F2(9) for the
B209: Contractor's Design for the following item(s):
A211: 13.4.1 | C211: Noise Barrier Panels and Sub-frames for Noise Barrier NB09 (Bay NB09-01P to 04P) | J211: $
A213: 13.4.2 | C213: Photovoltaic (PV) System for Noise Barrier NB09 | J213: $
A215: 13.5 | B215: Miscellanous
A217: 13.5.1 | B217: Completion of installation of drainage | J217: $
A219: 13.5.2 | B219: Completion of installation of watermains | J219: $
A221: 13.5.3 | B221: Completion of diversion of existing utilities | J221: $
A223: 13.5.4 | B223: Completion of reinstatement of existing footpath | J223: $
A225: 13.5.5 | B225: Completion of reinstatement of carriageway | J225: $
A227: 13.6 | B227: Additional items required by the Contractor (to be inserted by rhe Contractor) | J227: $
I266: Total carried to collection | J266: $
A267: Item | B267: Activity | J267: Prices (HK$)
B269: Collection from Page AS.S13/1 | J269: $
B270: Collection from Page AS.S13/2 | J270: $
B271: Collection from Page AS.S13/3 | J271: $
B272: Collection from Page AS.S13/4 | J272: $
I328: Total Prices of Schedule No. 13 Carried to Grand Summary of the Activity Schedule | J328: $

Sheet A14
A2: THE GOVERNMENT OF THE HONG KONG SPECIAL ADMINISTRATIVE REGION
A4: HIGHWAYS DEPARTMENT
A5: MAJOR WORKS PROJECT MANAGEMENT OFFICE
A7: CONTRACT NO. HY/2021/06
A8: RETROFITTING OF NOISE BARRIERS ON PO LAM ROAD NORTH AND PO NING ROAD
A10: ACTIVITY SCHEDULE
A12: Schedule No. 14 - Noise Barriers NB10
A14: Item | B14: Activity | J14: Prices (HK$)
A16: 14 | B16: Noise Barriers NB10
A18: 14.1 | B18: Piling Works
A20: 14.1.1 | B20: Establishment of piling plant | J20: $
A22: 14.1.2 | B22: Pre-drilling works | J22: $
A24: 14.1.3 | B24: Piling
A26: 14.1.3.1 | B26: Excavation of piles
A28: 14.1.3.1.1 | B28: Completion of excavation of piles for Bay NB10-01P | J28: $
A29: 14.1.3.1.2 | B29: Completion of excavation of piles for Bay NB10-02P | J29: $
A30: 14.1.3.1.3 | B30: Completion of excavation of piles for Bay NB10-03P | J30: $
A31: 14.1.3.1.4 | B31: Completion of excavation of piles for Bay NB10-04P | J31: $
A34: 14.1.3.2 | B34: Installation of reinforcement for piles
A36: 14.1.3.2.1 | B36: Completion of installation of reinforcement of piles for Bay NB10-01P | J36: $
A37: 14.1.3.2.2 | B37: Completion of installation of reinforcement of piles for Bay NB10-02P | J37: $
A38: 14.1.3.2.3 | B38: Completion of installation of reinforcement of piles for Bay NB10-03P | J38: $
A39: 14.1.3.2.4 | B39: Completion of installation of reinforcement of piles for Bay NB10-04P | J39: $
A42: 14.1.3.3 | B42: Completion of piling works
A44: 14.1.3.3.1 | B44: Completion of all piling works for Bay NB10-01P | J44: $
A45: 14.1.3.3.2 | B45: Completion of all piling works for Bay NB10-02P | J45: $
A46: 14.1.3.3.3 | B46: Completion of all piling works for Bay NB10-03P | J46: $
A47: 14.1.3.3.4 | B47: Completion of all piling works for Bay NB10-04P | J47: $
A50: 14.1.4 | B50: Preliminary Pile
A52: 14.1.4.1 | B52: Completion of one preliminary pile | J52: $
A53: 14.1.4.2 | B53: Completion of all pile tests for preliminary pile | J53: $
I76: Total carried to collection | J76: $
A77: Item | B77: Activity | J77: Prices (HK$)
A79: 14.2 | B79: Substructure
A81: 14.2.1 | B81: Excavation for pile cap
A83: 14.2.1.1 | B83: Completion of excavation of pile cap for Bay NB10-01P | J83: $
A84: 14.2.1.2 | B84: Completion of excavation of pile cap for Bay NB10-02P | J84: $
A85: 14.2.1.3 | B85: Completion of excavation of pile cap for Bay NB10-03P | J85: $
A86: 14.2.1.4 | B86: Completion of excavation of pile cap for Bay NB10-04P | J86: $
A89: 14.2.2 | B89: Fixing of reinforcement
A91: 14.2.2.1 | B91: Completion of fixing of reinforcement of pile cap and stem wall for Bay NB10-01P | J91: $
A92: 14.2.2.2 | B92: Completion of fixing of reinforcement of pile cap and stem wall for Bay NB10-02P | J92: $
A93: 14.2.2.3 | B93: Completion of fixing of reinforcement of pile cap and stem wall for Bay NB10-03P | J93: $
A94: 14.2.2.4 | B94: Completion of fixing of reinforcement of pile cap and stem wall for Bay NB10-04P | J94: $
A97: 14.2.3 | B97: Completion of pile caps with stem wall
A99: 14.2.3.1 | B99: Completion of all pile caps with stem wall and movement joints for Bay NB10-01P | J99: $
A100: 14.2.3.2 | B100: Completion of all pile caps with stem wall and movement joints for Bay NB10-02P | J100: $
A101: 14.2.3.3 | B101: Completion of all pile caps with stem wall and movement joints for Bay NB10-03P | J101: $
A102: 14.2.3.4 | B102: Completion of all pile caps with stem wall and movement joints for Bay NB10-04P | J102: $
I139: Total carried to collection | J139: $
A140: Item | B140: Activity | J140: Prices (HK$)
A142: 14.3 | B142: Superstructure
A144: 14.3.1 | B144: Installation of vertical posts for noise barriers
A146: 14.3.1.1 | B146: Completion of installation of vertical posts of noise barriers for Bay NB10-01P | J146: $
A147: 14.3.1.2 | B147: Completion of installation of vertical posts of noise barriers for Bay NB10-02P | J147: $
A148: 14.3.1.3 | B148: Completion of installation of vertical posts of noise barriers for Bay NB10-03P | J148: $
A149: 14.3.1.4 | B149: Completion of installation of vertical posts of noise barriers for Bay NB10-04P | J149: $
A151: 14.3.2 | B151: Installation of tie beams for noise barriers
A153: 14.3.2.1 | B153: Completion of installation of tie bems of noise barriers for Bay NB10-01P | J153: $
A154: 14.3.2.2 | B154: Completion of installation of tie bems of noise barriers for Bay NB10-02P | J154: $
A155: 14.3.2.3 | B155: Completion of installation of tie bems of noise barriers for Bay NB10-03P | J155: $
A156: 14.3.2.4 | B156: Completion of installation of tie bems of noise barriers for Bay NB10-04P | J156: $
I202: Total carried to collection | J202: $
A203: Item | B203: Activity | J203: Prices (HK$)
A205: 14.4 | B205: Contractor's Design
B207: Tenderer is required to complete a detailed Schedule of Rates in accordance with ACC Clause F2(9) for the
B208: Contractor's Design for the following item(s):
A210: 14.4.1 | C210: Noise Barrier Panels and Sub-frames for Noise Barrier NB10 (Bay NB10-01P to 04P) | J210: $
A212: 14.4.2 | C212: Photovoltaic (PV) System for Noise Barrier NB10 | J212: $
A214: 14.5 | B214: Miscellanous
A216: 14.5.1 | B216: Completion of installation of drainage | J216: $
A218: 14.5.2 | B218: Completion of installation of watermains | J218: $
A220: 14.5.3 | B220: Completion of diversion of existing utilities | J220: $
A222: 14.5.4 | B222: Completion of reinstatement of existing footpath | J222: $
A224: 14.5.5 | B224: Completion of reinstatement of carriageway | J224: $
A226: 14.6 | B226: Additional items required by the Contractor (to be inserted by rhe Contractor) | J226: $
I265: Total carried to collection | J265: $
A266: Item | B266: Activity | J266: Prices (HK$)
B268: Collection from Page AS.S14/1 | J268: $
B269: Collection from Page AS.S14/2 | J269: $
B270: Collection from Page AS.S14/3 | J270: $
B271: Collection from Page AS.S14/4 | J271: $
I328: Total Prices of Schedule No. 14 Carried to Grand Summary of the Activity Schedule | J328: $

Sheet A15
A2: THE GOVERNMENT OF THE HONG KONG SPECIAL ADMINISTRATIVE REGION
A4: HIGHWAYS DEPARTMENT
A5: MAJOR WORKS PROJECT MANAGEMENT OFFICE
A7: CONTRACT NO. HY/2021/06
A8: RETROFITTING OF NOISE BARRIERS ON PO LAM ROAD NORTH AND PO NING ROAD
A10: ACTIVITY SCHEDULE
A12: Schedule No. 15 - Noise Barriers NB11
A14: Item | B14: Activity | J14: Prices (HK$)
A16: 15 | B16: Noise Barriers NB11
A18: 15.1 | B18: Piling Works
A20: 15.1.1 | B20: Establishment of piling plant | J20: $
A22: 15.1.2 | B22: Pre-drilling works | J22: $
A24: 15.1.3 | B24: Piling
A26: 15.1.3.1 | B26: Excavation of piles
A28: 15.1.3.1.1 | B28: Completion of excavation of piles for Bay NB11-01P | J28: $
A29: 15.1.3.1.2 | B29: Completion of excavation of piles for Bay NB11-02P | J29: $
A30: 15.1.3.1.3 | B30: Completion of excavation of piles for Bay NB11-03P | J30: $
A31: 15.1.3.1.4 | B31: Completion of excavation of piles for Bay NB11-04P | J31: $
A32: 15.1.3.1.5 | B32: Completion of excavation of piles for Bay NB11-05P | J32: $
A34: 15.1.3.2 | B34: Installation of reinforcement for piles
A36: 15.1.3.2.1 | B36: Completion of installation of reinforcement of piles for Bay NB11-01P | J36: $
A37: 15.1.3.2.2 | B37: Completion of installation of reinforcement of piles for Bay NB11-02P | J37: $
A38: 15.1.3.2.3 | B38: Completion of installation of reinforcement of piles for Bay NB11-03P | J38: $
A39: 15.1.3.2.4 | B39: Completion of installation of reinforcement of piles for Bay NB11-04P | J39: $
A40: 15.1.3.2.5 | B40: Completion of installation of reinforcement of piles for Bay NB11-05P | J40: $
A42: 15.1.3.3 | B42: Completion of piling works
A44: 15.1.3.3.1 | B44: Completion of all piling works for Bay NB11-01P | J44: $
A45: 15.1.3.3.2 | B45: Completion of all piling works for Bay NB11-02P | J45: $
A46: 15.1.3.3.3 | B46: Completion of all piling works for Bay NB11-03P | J46: $
A47: 15.1.3.3.4 | B47: Completion of all piling works for Bay NB11-04P | J47: $
A48: 15.1.3.3.5 | B48: Completion of all piling works for Bay NB11-05P | J48: $
A50: 15.1.4 | B50: Preliminary Pile
A52: 15.1.4.1 | B52: Completion of one preliminary pile | J52: $
A53: 15.1.4.2 | B53: Completion of all pile tests for preliminary pile | J53: $
I76: Total carried to collection | J76: $
A77: Item | B77: Activity | J77: Prices (HK$)
A79: 15.2 | B79: Substructure
A81: 15.2.1 | B81: Excavation for pile cap
A83: 15.2.1.1 | B83: Completion of excavation of pile cap for Bay NB11-01P | J83: $
A84: 15.2.1.2 | B84: Completion of excavation of pile cap for Bay NB11-02P | J84: $
A85: 15.2.1.3 | B85: Completion of excavation of pile cap for Bay NB11-03P | J85: $
A86: 15.2.1.4 | B86: Completion of excavation of pile cap for Bay NB11-04P | J86: $
A87: 15.2.1.5 | B87: Completion of excavation of pile cap for Bay NB11-05P | J87: $
A89: 15.2.2 | B89: Fixing of reinforcement
A91: 15.2.2.1 | B91: Completion of fixing of reinforcement of pile cap and stem wall for Bay NB11-01P | J91: $
A92: 15.2.2.2 | B92: Completion of fixing of reinforcement of pile cap and stem wall for Bay NB11-02P | J92: $
A93: 15.2.2.3 | B93: Completion of fixing of reinforcement of pile cap and stem wall for Bay NB11-03P | J93: $
A94: 15.2.2.4 | B94: Completion of fixing of reinforcement of pile cap and stem wall for Bay NB11-04P | J94: $
A95: 15.2.2.5 | B95: Completion of fixing of reinforcement of pile cap and stem wall for Bay NB11-05P | J95: $
A97: 15.2.3 | B97: Completion of pile caps with stem wall
A99: 15.2.3.1 | B99: Completion of all pile caps with stem wall and movement joints for Bay NB11-01P | J99: $
A100: 15.2.3.2 | B100: Completion of all pile caps with stem wall and movement joints for Bay NB11-02P | J100: $
A101: 15.2.3.3 | B101: Completion of all pile caps with stem wall and movement joints for Bay NB11-03P | J101: $
A102: 15.2.3.4 | B102: Completion of all pile caps with stem wall and movement joints for Bay NB11-04P | J102: $
A103: 15.2.3.5 | B103: Completion of all pile caps with stem wall and movement joints for Bay NB11-05P | J103: $
I139: Total carried to collection | J139: $
A140: Item | B140: Activity | J140: Prices (HK$)
A142: 15.3 | B142: Superstructure
A144: 15.3.1 | B144: Installation of vertical posts for noise barriers
A146: 15.3.1.1 | B146: Completion of installation of vertical posts of noise barriers for Bay NB11-01P | J146: $
A147: 15.3.1.2 | B147: Completion of installation of vertical posts of noise barriers for Bay NB11-02P | J147: $
A148: 15.3.1.3 | B148: Completion of installation of vertical posts of noise barriers for Bay NB11-03P | J148: $
A149: 15.3.1.4 | B149: Completion of installation of vertical posts of noise barriers for Bay NB11-04P | J149: $
A150: 15.3.1.5 | B150: Completion of installation of vertical posts of noise barriers for Bay NB11-05P | J150: $
A152: 15.3.2 | B152: Installation of tie beams for noise barriers
A154: 15.3.2.1 | B154: Completion of installation of tie bems of noise barriers for Bay NB11-01P | J154: $
A155: 15.3.2.2 | B155: Completion of installation of tie bems of noise barriers for Bay NB11-02P | J155: $
A156: 15.3.2.3 | B156: Completion of installation of tie bems of noise barriers for Bay NB11-03P | J156: $
A157: 15.3.2.4 | B157: Completion of installation of tie bems of noise barriers for Bay NB11-04P | J157: $
A158: 15.3.2.5 | B158: Completion of installation of tie bems of noise barriers for Bay NB11-05P | J158: $
I202: Total carried to collection | J202: $
A203: Item | B203: Activity | J203: Prices (HK$)
A205: 15.4 | B205: Contractor's Design
B207: Tenderer is required to complete a detailed Schedule of Rates in accordance with ACC Clause F2(9) for the
B208: Contractor's Design for the following item(s):
A210: 15.4.1 | C210: Noise Barrier Panels and Sub-frames for Noise Barrier NB11 (Bay NB11-01P to 05P) | J210: $
A212: 15.5 | B212: Miscellanous
A214: 15.5.1 | B214: Completion of installation of drainage | J214: $
A216: 15.5.2 | B216: Completion of installation of watermains | J216: $
A218: 15.5.3 | B218: Completion of diversion of existing utilities | J218: $
A220: 15.5.4 | B220: Completion of reinstatement of existing footpath | J220: $
A222: 15.5.5 | B222: Completion of reinstatement of carriageway | J222: $
A224: 15.6 | B224: Additional items required by the Contractor (to be inserted by rhe Contractor) | J224: $
I265: Total carried to collection | J265: $
A266: Item | B266: Activity | J266: Prices (HK$)
B268: Collection from Page AS.S15/1 | J268: $
B269: Collection from Page AS.S15/2 | J269: $
B270: Collection from Page AS.S15/3 | J270: $
B271: Collection from Page AS.S15/4 | J271: $
I328: Total Prices of Schedule No. 15 Carried to Grand Summary of the Activity Schedule | J328: $

Sheet A16
A2: THE GOVERNMENT OF THE HONG KONG SPECIAL ADMINISTRATIVE REGION
A4: HIGHWAYS DEPARTMENT
A5: MAJOR WORKS PROJECT MANAGEMENT OFFICE
A7: CONTRACT NO. HY/2021/06
A8: RETROFITTING OF NOISE BARRIERS ON PO LAM ROAD NORTH AND PO NING ROAD
A10: ACTIVITY SCHEDULE
A12: Schedule No. 16 - Noise Barriers NB12
A14: Item | B14: Activity | J14: Prices (HK$)
A16: 16 | B16: Noise Barriers NB12
A18: 16.1 | B18: Piling Works
A20: 16.1.1 | B20: Establishment of piling plant | J20: $
A22: 16.1.2 | B22: Pre-drilling works | J22: $
A24: 16.1.3 | B24: Piling
A26: 16.1.3.1 | B26: Excavation of piles
A28: 16.1.3.1.1 | B28: Completion of excavation of piles for Bay NB12-01P | J28: $
A29: 16.1.3.1.2 | B29: Completion of excavation of piles for Bay NB12-02P | J29: $
A30: 16.1.3.1.3 | B30: Completion of excavation of piles for Bay NB12-03P | J30: $
A32: 16.1.3.2 | B32: Installation of reinforcement for piles
A34: 16.1.3.2.1 | B34: Completion of installation of reinforcement of piles for Bay NB12-01P | J34: $
A35: 16.1.3.2.2 | B35: Completion of installation of reinforcement of piles for Bay NB12-02P | J35: $
A36: 16.1.3.2.3 | B36: Completion of installation of reinforcement of piles for Bay NB12-03P | J36: $
A38: 16.1.3.3 | B38: Completion of piling works
A40: 16.1.3.3.1 | B40: Completion of all piling works for Bay NB12-01P | J40: $
A41: 16.1.3.3.2 | B41: Completion of all piling works for Bay NB12-02P | J41: $
A42: 16.1.3.3.3 | B42: Completion of all piling works for Bay NB12-03P | J42: $
I76: Total carried to collection | J76: $
A77: Item | B77: Activity | J77: Prices (HK$)
A79: 16.2 | B79: Substructure
A81: 16.2.1 | B81: Excavation for pile cap
A83: 16.2.1.1 | B83: Completion of excavation of pile cap for Bay NB12-01P | J83: $
A84: 16.2.1.2 | B84: Completion of excavation of pile cap for Bay NB12-02P | J84: $
A85: 16.2.1.3 | B85: Completion of excavation of pile cap for Bay NB12-03P | J85: $
A87: 16.2.2 | B87: Fixing of reinforcement
A89: 16.2.2.1 | B89: Completion of fixing of reinforcement of pile cap and stem wall for Bay NB12-01P | J89: $
A90: 16.2.2.2 | B90: Completion of fixing of reinforcement of pile cap and stem wall for Bay NB12-02P | J90: $
A91: 16.2.2.3 | B91: Completion of fixing of reinforcement of pile cap and stem wall for Bay NB12-03P | J91: $
A93: 16.2.3 | B93: Completion of pile caps with stem wall
A95: 16.2.3.1 | B95: Completion of all pile caps with stem wall and movement joints for Bay NB12-01P | J95: $
A96: 16.2.3.2 | B96: Completion of all pile caps with stem wall and movement joints for Bay NB12-02P | J96: $
A97: 16.2.3.3 | B97: Completion of all pile caps with stem wall and movement joints for Bay NB12-03P | J97: $
I139: Total carried to collection | J139: $
A140: Item | B140: Activity | J140: Prices (HK$)
A142: 16.3 | B142: Superstructure
A144: 16.3.1 | B144: Installation of vertical posts for noise barriers
A146: 16.3.1.1 | B146: Completion of installation of vertical posts of noise barriers for Bay NB12-01P | J146: $
A147: 16.3.1.2 | B147: Completion of installation of vertical posts of noise barriers for Bay NB12-02P | J147: $
A148: 16.3.1.3 | B148: Completion of installation of vertical posts of noise barriers for Bay NB12-03P | J148: $
A150: 16.3.2 | B150: Installation of tie beams for noise barriers
A152: 16.3.2.1 | B152: Completion of installation of tie bems of noise barriers for Bay NB12-01P | J152: $
A153: 16.3.2.2 | B153: Completion of installation of tie bems of noise barriers for Bay NB12-02P | J153: $
A154: 16.3.2.3 | B154: Completion of installation of tie bems of noise barriers for Bay NB12-03P | J154: $
I202: Total carried to collection | J202: $
A203: Item | B203: Activity | J203: Prices (HK$)
A205: 16.4 | B205: Contractor's Design
B207: Tenderer is required to complete a detailed Schedule of Rates in accordance with ACC Clause F2(9) for the
B208: Contractor's Design for the following item(s):
A210: 16.4.1 | C210: Noise Barrier Panels and Sub-frames for Noise Barrier NB12 (Bay NB12-01P to 03P) | J210: $
A212: 16.5 | B212: Miscellanous
A214: 16.5.1 | B214: Completion of installation of drainage | J214: $
A216: 16.5.2 | B216: Completion of installation of watermains | J216: $
A218: 16.5.3 | B218: Completion of diversion of existing utilities | J218: $
A220: 16.5.4 | B220: Completion of reinstatement of existing footpath | J220: $
A222: 16.5.5 | B222: Completion of reinstatement of carriageway | J222: $
A224: 16.6 | B224: Additional items required by the Contractor (to be inserted by rhe Contractor) | J224: $
I265: Total carried to collection | J265: $
A266: Item | B266: Activity | J266: Prices (HK$)
B268: Collection from Page AS.S16/1 | J268: $
B269: Collection from Page AS.S16/2 | J269: $
B270: Collection from Page AS.S16/3 | J270: $
B271: Collection from Page AS.S16/4 | J271: $
I328: Total Prices of Schedule No. 16 Carried to Grand Summary of the Activity Schedule | J328: $

Sheet A17
A2: THE GOVERNMENT OF THE HONG KONG SPECIAL ADMINISTRATIVE REGION
A4: HIGHWAYS DEPARTMENT
A5: MAJOR WORKS PROJECT MANAGEMENT OFFICE
A7: CONTRACT NO. HY/2021/06
A8: RETROFITTING OF NOISE BARRIERS ON PO LAM ROAD NORTH AND PO NING ROAD
A10: ACTIVITY SCHEDULE
A12: Schedule No. 17 - Noise Barriers NB13
A14: Item | B14: Activity | J14: Prices (HK$)
A16: 17 | B16: Noise Barriers NB13
A18: 17.1 | B18: Piling Works
A20: 17.1.1 | B20: Establishment of piling plant | J20: $
A22: 17.1.2 | B22: Pre-drilling works | J22: $
A24: 17.1.3 | B24: Piling
A26: 17.1.3.1 | B26: Excavation of piles
A28: 17.1.3.1.1 | B28: Completion of excavation of piles for Bay NB13-01P | J28: $
A29: 17.1.3.1.2 | B29: Completion of excavation of piles for Bay NB13-02P | J29: $
A30: 17.1.3.1.3 | B30: Completion of excavation of piles for Bay NB13-03P | J30: $
A33: 17.1.3.2 | B33: Installation of reinforcement for piles
A35: 17.1.3.2.1 | B35: Completion of installation of reinforcement of piles for Bay NB13-01P | J35: $
A36: 17.1.3.2.2 | B36: Completion of installation of reinforcement of piles for Bay NB13-02P | J36: $
A37: 17.1.3.2.3 | B37: Completion of installation of reinforcement of piles for Bay NB13-03P | J37: $
A40: 17.1.3.3 | B40: Completion of piling works
A42: 17.1.3.3.1 | B42: Completion of all piling works for Bay NB13-01P | J42: $
A43: 17.1.3.3.2 | B43: Completion of all piling works for Bay NB13-02P | J43: $
A44: 17.1.3.3.3 | B44: Completion of all piling works for Bay NB13-03P | J44: $
A47: 17.1.4 | B47: Preliminary Pile
A49: 17.1.4.1 | B49: Completion of one preliminary pile | J49: $
A50: 17.1.4.2 | B50: Completion of all pile tests for preliminary pile | J50: $
I76: Total carried to collection | J76: $
A77: Item | B77: Activity | J77: Prices (HK$)
A79: 17.2 | B79: Substructure
A81: 17.2.1 | B81: Excavation for pile cap
A83: 17.2.1.1 | B83: Completion of excavation of pile cap for Bay NB13-01P | J83: $
A84: 17.2.1.2 | B84: Completion of excavation of pile cap for Bay NB13-02P | J84: $
A85: 17.2.1.3 | B85: Completion of excavation of pile cap for Bay NB13-03P | J85: $
A88: 17.2.2 | B88: Fixing of reinforcement
A90: 17.2.2.1 | B90: Completion of fixing of reinforcement of pile cap and stem wall for Bay NB13-01P | J90: $
A91: 17.2.2.2 | B91: Completion of fixing of reinforcement of pile cap and stem wall for Bay NB13-02P | J91: $
A92: 17.2.2.3 | B92: Completion of fixing of reinforcement of pile cap and stem wall for Bay NB13-03P | J92: $
A95: 17.2.3 | B95: Completion of pile caps with stem wall
A97: 17.2.3.1 | B97: Completion of all pile caps with stem wall and movement joints for Bay NB13-01P | J97: $
A98: 17.2.3.2 | B98: Completion of all pile caps with stem wall and movement joints for Bay NB13-02P | J98: $
A99: 17.2.3.3 | B99: Completion of all pile caps with stem wall and movement joints for Bay NB13-03P | J99: $
I139: Total carried to collection | J139: $
A140: Item | B140: Activity | J140: Prices (HK$)
A142: 17.3 | B142: Superstructure
A144: 17.3.1 | B144: Installation of vertical posts for noise barriers
A146: 17.3.1.1 | B146: Completion of installation of vertical posts of noise barriers for Bay NB13-01P | J146: $
A147: 17.3.1.2 | B147: Completion of installation of vertical posts of noise barriers for Bay NB13-02P | J147: $
A148: 17.3.1.3 | B148: Completion of installation of vertical posts of noise barriers for Bay NB13-03P | J148: $
A150: 17.3.2 | B150: Installation of tie beams for noise barriers
A152: 17.3.2.1 | B152: Completion of installation of tie bems of noise barriers for Bay NB13-01P | J152: $
A153: 17.3.2.2 | B153: Completion of installation of tie bems of noise barriers for Bay NB13-02P | J153: $
A154: 17.3.2.3 | B154: Completion of installation of tie bems of noise barriers for Bay NB13-03P | J154: $
I202: Total carried to collection | J202: $
A203: Item | B203: Activity | J203: Prices (HK$)
A205: 17.4 | B205: Contractor's Design
B207: Tenderer is required to complete a detailed Schedule of Rates in accordance with ACC Clause F2(9) for the
B208: Contractor's Design for the following item(s):
A210: 17.4.1 | C210: Noise Barrier Panels and Sub-frames for Noise Barrier NB13 (Bay NB13-01P to 03P) | J210: $
A212: 17.5 | B212: Miscellanous
A214: 17.5.1 | B214: Completion of installation of drainage | J214: $
A216: 17.5.2 | B216: Completion of installation of watermains | J216: $
A218: 17.5.3 | B218: Completion of diversion of existing utilities | J218: $
A220: 17.5.4 | B220: Completion of reinstatement of existing footpath | J220: $
A222: 17.5.5 | B222: Completion of reinstatement of carriageway | J222: $
A224: 17.6 | B224: Additional items required by the Contractor (to be inserted by rhe Contractor) | J224: $
I265: Total carried to collection | J265: $
A266: Item | B266: Activity | J266: Prices (HK$)
B268: Collection from Page AS.S17/1 | J268: $
B269: Collection from Page AS.S17/2 | J269: $
B270: Collection from Page AS.S17/3 | J270: $
B271: Collection from Page AS.S17/4 | J271: $
J272: $
I328: Total Prices of Schedule No. 17 Carried to Grand Summary of the Activity Schedule | J328: $

Sheet A18
A2: THE GOVERNMENT OF THE HONG KONG SPECIAL ADMINISTRATIVE REGION
A4: HIGHWAYS DEPARTMENT
A5: MAJOR WORKS PROJECT MANAGEMENT OFFICE
A7: CONTRACT NO. HY/2021/06
A8: RETROFITTING OF NOISE BARRIERS ON PO LAM ROAD NORTH AND PO NING ROAD
A10: ACTIVITY SCHEDULE
A12: Schedule No. 18 - Noise Barriers NB14
A14: Item | B14: Activity | J14: Prices (HK$)
A16: 18 | B16: Noise Barriers NB14
A18: 18.1 | B18: Piling Works
A20: 18.1.1 | B20: Establishment of piling plant | J20: $
A22: 18.1.2 | B22: Pre-drilling works | J22: $
A24: 18.1.3 | B24: Piling
A26: 18.1.3.1 | B26: Excavation of piles
A28: 18.1.3.1.1 | B28: Completion of excavation of piles for Bay NB14-01P | J28: $
A29: 18.1.3.1.2 | B29: Completion of excavation of piles for Bay NB14-02P | J29: $
A30: 18.1.3.1.3 | B30: Completion of excavation of piles for Bay NB14-03P | J30: $
A31: 18.1.3.1.4 | B31: Completion of excavation of piles for Bay NB14-04P | J31: $
A34: 18.1.3.2 | B34: Installation of reinforcement for piles
A36: 18.1.3.2.1 | B36: Completion of installation of reinforcement of piles for Bay NB14-01P | J36: $
A37: 18.1.3.2.2 | B37: Completion of installation of reinforcement of piles for Bay NB14-02P | J37: $
A38: 18.1.3.2.3 | B38: Completion of installation of reinforcement of piles for Bay NB14-03P | J38: $
A39: 18.1.3.2.4 | B39: Completion of installation of reinforcement of piles for Bay NB14-04P | J39: $
A42: 18.1.3.3 | B42: Completion of piling works
A44: 18.1.3.3.1 | B44: Completion of all piling works for Bay NB14-01P | J44: $
A45: 18.1.3.3.2 | B45: Completion of all piling works for Bay NB14-02P | J45: $
A46: 18.1.3.3.3 | B46: Completion of all piling works for Bay NB14-03P | J46: $
A47: 18.1.3.3.4 | B47: Completion of all piling works for Bay NB14-04P | J47: $
I76: Total carried to collection | J76: $
A77: Item | B77: Activity | J77: Prices (HK$)
A79: 18.2 | B79: Substructure
A81: 18.2.1 | B81: Excavation for pile cap
A83: 18.2.1.1 | B83: Completion of excavation of pile cap for Bay NB14-01P | J83: $
A84: 18.2.1.2 | B84: Completion of excavation of pile cap for Bay NB14-02P | J84: $
A85: 18.2.1.3 | B85: Completion of excavation of pile cap for Bay NB14-03P | J85: $
A86: 18.2.1.4 | B86: Completion of excavation of pile cap for Bay NB14-04P | J86: $
A89: 18.2.2 | B89: Fixing of reinforcement
A91: 18.2.2.1 | B91: Completion of fixing of reinforcement of pile cap and stem wall for Bay NB14-01P | J91: $
A92: 18.2.2.2 | B92: Completion of fixing of reinforcement of pile cap and stem wall for Bay NB14-02P | J92: $
A93: 18.2.2.3 | B93: Completion of fixing of reinforcement of pile cap and stem wall for Bay NB14-03P | J93: $
A94: 18.2.2.4 | B94: Completion of fixing of reinforcement of pile cap and stem wall for Bay NB14-04P | J94: $
A97: 18.2.3 | B97: Completion of pile caps with stem wall
A99: 18.2.3.1 | B99: Completion of all pile caps with stem wall and movement joints for Bay NB14-01P | J99: $
A100: 18.2.3.2 | B100: Completion of all pile caps with stem wall and movement joints for Bay NB14-02P | J100: $
A101: 18.2.3.3 | B101: Completion of all pile caps with stem wall and movement joints for Bay NB14-03P | J101: $
A102: 18.2.3.4 | B102: Completion of all pile caps with stem wall and movement joints for Bay NB14-04P | J102: $
I139: Total carried to collection | J139: $
A140: Item | B140: Activity | J140: Prices (HK$)
A142: 18.3 | B142: Superstructure
A144: 18.3.1 | B144: Installation of vertical posts for noise barriers
A146: 18.3.1.1 | B146: Completion of installation of vertical posts of noise barriers for Bay NB14-01P | J146: $
A147: 18.3.1.2 | B147: Completion of installation of vertical posts of noise barriers for Bay NB14-02P | J147: $
A148: 18.3.1.3 | B148: Completion of installation of vertical posts of noise barriers for Bay NB14-03P | J148: $
A149: 18.3.1.4 | B149: Completion of installation of vertical posts of noise barriers for Bay NB14-04P | J149: $
A151: 18.3.2 | B151: Installation of tie beams for noise barriers
A153: 18.3.2.1 | B153: Completion of installation of tie bems of noise barriers for Bay NB14-01P | J153: $
A154: 18.3.2.2 | B154: Completion of installation of tie bems of noise barriers for Bay NB14-02P | J154: $
A155: 18.3.2.3 | B155: Completion of installation of tie bems of noise barriers for Bay NB14-03P | J155: $
A156: 18.3.2.4 | B156: Completion of installation of tie bems of noise barriers for Bay NB14-04P | J156: $
I202: Total carried to collection | J202: $
A203: Item | B203: Activity | J203: Prices (HK$)
A205: 18.4 | B205: Contractor's Design
B207: Tenderer is required to complete a detailed Schedule of Rates in accordance with ACC Clause F2(9) for the
B208: Contractor's Design for the following item(s):
A210: 18.4.1 | C210: Noise Barrier Panels and Sub-frames for Noise Barrier NB14 (Bay NB14-01P to 04P) | J210: $
A212: 18.5 | B212: Miscellanous
A214: 18.5.1 | B214: Completion of installation of drainage | J214: $
A216: 18.5.2 | B216: Completion of installation of watermains | J216: $
A218: 18.5.3 | B218: Completion of diversion of existing utilities | J218: $
A220: 18.5.4 | B220: Completion of reinstatement of existing footpath | J220: $
A222: 18.5.5 | B222: Completion of reinstatement of carriageway | J222: $
A224: 18.6 | B224: Additional items required by the Contractor (to be inserted by rhe Contractor) | J224: $
I265: Total carried to collection | J265: $
A266: Item | B266: Activity | J266: Prices (HK$)
B268: Collection from Page AS.S18/1 | J268: $
B269: Collection from Page AS.S18/2 | J269: $
B270: Collection from Page AS.S18/3 | J270: $
B271: Collection from Page AS.S18/4 | J271: $
I328: Total Prices of Schedule No. 18 Carried to Grand Summary of the Activity Schedule | J328: $

Sheet A19
A2: THE GOVERNMENT OF THE HONG KONG SPECIAL ADMINISTRATIVE REGION
A4: HIGHWAYS DEPARTMENT
A5: MAJOR WORKS PROJECT MANAGEMENT OFFICE
A7: CONTRACT NO. HY/2021/06
A8: RETROFITTING OF NOISE BARRIERS ON PO LAM ROAD NORTH AND PO NING ROAD
A10: ACTIVITY SCHEDULE
A12: Schedule No. 19 - Noise Barriers NB15
A14: Item | B14: Activity | J14: Prices (HK$)
A16: 19 | B16: Noise Barriers NB15
A18: 19.1 | B18: Piling Works
A20: 19.1.1 | B20: Establishment of piling plant | J20: $
A22: 19.1.2 | B22: Pre-drilling works | J22: $
A24: 19.1.3 | B24: Piling
A26: 19.1.3.1 | B26: Excavation of piles
A28: 19.1.3.1.1 | B28: Completion of excavation of piles for Bay NB15-01P | J28: $
A29: 19.1.3.1.2 | B29: Completion of excavation of piles for Bay NB15-02P | J29: $
A30: 19.1.3.1.3 | B30: Completion of excavation of piles for Bay NB15-03P | J30: $
A31: 19.1.3.1.4 | B31: Completion of excavation of piles for Bay NB15-04P | J31: $
A32: 19.1.3.1.5 | B32: Completion of excavation of piles for Bay NB15-05P | J32: $
A34: 19.1.3.2 | B34: Installation of reinforcement for piles
A36: 19.1.3.2.1 | B36: Completion of installation of reinforcement of piles for Bay NB15-01P | J36: $
A37: 19.1.3.2.2 | B37: Completion of installation of reinforcement of piles for Bay NB15-02P | J37: $
A38: 19.1.3.2.3 | B38: Completion of installation of reinforcement of piles for Bay NB15-03P | J38: $
A39: 19.1.3.2.4 | B39: Completion of installation of reinforcement of piles for Bay NB15-04P | J39: $
A40: 19.1.3.2.5 | B40: Completion of installation of reinforcement of piles for Bay NB15-05P | J40: $
A42: 19.1.3.3 | B42: Completion of piling works
A44: 19.1.3.3.1 | B44: Completion of all piling works for Bay NB15-01P | J44: $
A45: 19.1.3.3.2 | B45: Completion of all piling works for Bay NB15-02P | J45: $
A46: 19.1.3.3.3 | B46: Completion of all piling works for Bay NB15-03P | J46: $
A47: 19.1.3.3.4 | B47: Completion of all piling works for Bay NB15-04P | J47: $
A48: 19.1.3.3.5 | B48: Completion of all piling works for Bay NB15-05P | J48: $
A50: 19.1.4 | B50: Pile tests
A52: 19.1.4.1 | B52: Completion of all pile tests | J52: $
I76: Total carried to collection | J76: $
A77: Item | B77: Activity | J77: Prices (HK$)
A79: 19.2 | B79: Substructure
A81: 19.2.1 | B81: Excavation for pile cap
A83: 19.2.1.1 | B83: Completion of excavation of pile cap for Bay NB15-01P | J83: $
A84: 19.2.1.2 | B84: Completion of excavation of pile cap for Bay NB15-02P | J84: $
A85: 19.2.1.3 | B85: Completion of excavation of pile cap for Bay NB15-03P | J85: $
A86: 19.2.1.4 | B86: Completion of excavation of pile cap for Bay NB15-04P | J86: $
A87: 19.2.1.5 | B87: Completion of excavation of pile cap for Bay NB15-05P | J87: $
A89: 19.2.2 | B89: Fixing of reinforcement
A91: 19.2.2.1 | B91: Completion of fixing of reinforcement of pile cap and stem wall for Bay NB15-01P | J91: $
A92: 19.2.2.2 | B92: Completion of fixing of reinforcement of pile cap and stem wall for Bay NB15-02P | J92: $
A93: 19.2.2.3 | B93: Completion of fixing of reinforcement of pile cap and stem wall for Bay NB15-03P | J93: $
A94: 19.2.2.4 | B94: Completion of fixing of reinforcement of pile cap and stem wall for Bay NB15-04P | J94: $
A95: 19.2.2.5 | B95: Completion of fixing of reinforcement of pile cap and stem wall for Bay NB15-05P | J95: $
A97: 19.2.3 | B97: Completion of pile caps with stem wall
A99: 19.2.3.1 | B99: Completion of all pile caps with stem wall and movement joints for Bay NB15-01P | J99: $
A100: 19.2.3.2 | B100: Completion of all pile caps with stem wall and movement joints for Bay NB15-02P | J100: $
A101: 19.2.3.3 | B101: Completion of all pile caps with stem wall and movement joints for Bay NB15-03P | J101: $
A102: 19.2.3.4 | B102: Completion of all pile caps with stem wall and movement joints for Bay NB15-04P | J102: $
A103: 19.2.3.5 | B103: Completion of all pile caps with stem wall and movement joints for Bay NB15-05P | J103: $
I139: Total carried to collection | J139: $
A140: Item | B140: Activity | J140: Prices (HK$)
A142: 19.3 | B142: Superstructure
A144: 19.3.1 | B144: Installation of vertical posts for noise barriers
A146: 19.3.1.1 | B146: Completion of installation of vertical posts of noise barriers for Bay NB15-01P | J146: $
A147: 19.3.1.2 | B147: Completion of installation of vertical posts of noise barriers for Bay NB15-02P | J147: $
A148: 19.3.1.3 | B148: Completion of installation of vertical posts of noise barriers for Bay NB15-03P | J148: $
A149: 19.3.1.4 | B149: Completion of installation of vertical posts of noise barriers for Bay NB15-04P | J149: $
A150: 19.3.1.5 | B150: Completion of installation of vertical posts of noise barriers for Bay NB15-05P | J150: $
A152: 19.3.2 | B152: Installation of tie beams for noise barriers
A154: 19.3.2.1 | B154: Completion of installation of tie bems of noise barriers for Bay NB15-01P | J154: $
A155: 19.3.2.2 | B155: Completion of installation of tie bems of noise barriers for Bay NB15-02P | J155: $
A156: 19.3.2.3 | B156: Completion of installation of tie bems of noise barriers for Bay NB15-03P | J156: $
A157: 19.3.2.4 | B157: Completion of installation of tie bems of noise barriers for Bay NB15-04P | J157: $
A158: 19.3.2.5 | B158: Completion of installation of tie bems of noise barriers for Bay NB15-05P | J158: $
I202: Total carried to collection | J202: $
A203: Item | B203: Activity | J203: Prices (HK$)
A205: 19.4 | B205: Contractor's Design
B207: Tenderer is required to complete a detailed Schedule of Rates in accordance with ACC Clause F2(9) for the
B208: Contractor's Design for the following item(s):
A210: 19.4.1 | C210: Noise Barrier Panels and Sub-frames for Noise Barrier NB15 (Bay NB15-01P to 05P) | J210: $
A212: 19.5 | B212: Miscellanous
A214: 19.5.1 | B214: Completion of installation of drainage | J214: $
A216: 19.5.2 | B216: Completion of installation of watermains | J216: $
A218: 19.5.3 | B218: Completion of diversion of existing utilities | J218: $
A220: 19.5.4 | B220: Completion of reinstatement of existing footpath | J220: $
A222: 19.5.5 | B222: Completion of reinstatement of carriageway | J222: $
A224: 19.6 | B224: Additional items required by the Contractor (to be inserted by rhe Contractor) | J224: $
I265: Total carried to collection | J265: $
A266: Item | B266: Activity | J266: Prices (HK$)
B268: Collection from Page AS.S19/1 | J268: $
B269: Collection from Page AS.S19/2 | J269: $
B270: Collection from Page AS.S19/3 | J270: $
B271: Collection from Page AS.S19/4 | J271: $
J272: $
I328: Total Prices of Schedule No. 19 Carried to Grand Summary of the Activity Schedule | J328: $

Sheet A20
A2: THE GOVERNMENT OF THE HONG KONG SPECIAL ADMINISTRATIVE REGION
A4: HIGHWAYS DEPARTMENT
A5: MAJOR WORKS PROJECT MANAGEMENT OFFICE
A7: CONTRACT NO. HY/2021/06
A8: RETROFITTING OF NOISE BARRIERS ON PO LAM ROAD NORTH AND PO NING ROAD
A10: ACTIVITY SCHEDULE
A12: Schedule No. 20 - Noise Barriers NB16
A14: Item | B14: Activity | J14: Prices (HK$)
A16: 20 | B16: Noise Barriers NB16
A18: 20.1 | B18: Piling Works
A20: 20.1.1 | B20: Establishment of piling plant | J20: $
A22: 20.1.2 | B22: Pre-drilling works | J22: $
A24: 20.1.3 | B24: Piling
A26: 20.1.3.1 | B26: Excavation of piles
A28: 20.1.3.1.1 | B28: Completion of excavation of piles for Bay NB16-01P | J28: $
A29: 20.1.3.1.2 | B29: Completion of excavation of piles for Bay NB16-02P | J29: $
A30: 20.1.3.1.3 | B30: Completion of excavation of piles for Bay NB16-03P | J30: $
A31: 20.1.3.1.4 | B31: Completion of excavation of piles for Bay NB16-04P | J31: $
A32: 20.1.3.1.5 | B32: Completion of excavation of piles for Bay NB16-05P | J32: $
A33: 20.1.3.1.6 | B33: Completion of excavation of piles for Bay NB16-06P | J33: $
A34: 20.1.3.1.7 | B34: Completion of excavation of piles for Bay NB16-07P | J34: $
A35: 20.1.3.1.8 | B35: Completion of excavation of piles for Bay NB16-08P | J35: $
A36: 20.1.3.1.9 | B36: Completion of excavation of piles for Bay NB16-09P | J36: $
A37: 20.1.3.1.10 | B37: Completion of excavation of piles for Bay NB16-10P | J37: $
A38: 20.1.3.1.11 | B38: Completion of excavation of piles for Bay NB16-11P | J38: $
A39: 20.1.3.1.12 | B39: Completion of excavation of piles for Bay NB16-12P | J39: $
... A49: 20.1.3.1.22 | B49: Completion of excavation of piles for Bay NB16-22P | J49: $
A51: 20.1.3.2 | B51: Installation of reinforcement for piles
A53: 20.1.3.2.1 | B53: Completion of installation of reinforcement of piles for Bay NB16-01P | J53: $
A54: 20.1.3.2.2 | B54: Completion of installation of reinforcement of piles for Bay NB16-02P | J54: $
A55: 20.1.3.2.3 | B55: Completion of installation of reinforcement of piles for Bay NB16-03P | J55: $
A56: 20.1.3.2.4 | B56: Completion of installation of reinforcement of piles for Bay NB16-04P | J56: $
A57: 20.1.3.2.5 | B57: Completion of installation of reinforcement of piles for Bay NB16-05P | J57: $
A58: 20.1.3.2.6 | B58: Completion of installation of reinforcement of piles for Bay NB16-06P | J58: $
A59: 20.1.3.2.7 | B59: Completion of installation of reinforcement of piles for Bay NB16-07P | J59: $
A60: 20.1.3.2.8 | B60: Completion of installation of reinforcement of piles for Bay NB16-08P | J60: $
A61: 20.1.3.2.9 | B61: Completion of installation of reinforcement of piles for Bay NB16-09P | J61: $
A62: 20.1.3.2.10 | B62: Completion of installation of reinforcement of piles for Bay NB16-10P | J62: $
A63: 20.1.3.2.11 | B63: Completion of installation of reinforcement of piles for Bay NB16-11P | J63: $
A64: 20.1.3.2.12 | B64: Completion of installation of reinforcement of piles for Bay NB16-12P | J64: $
... A74: 20.1.3.2.22 | B74: Completion of installation of reinforcement of piles for Bay NB16-22P | J74: $
I77: Total carried to collection | J77: $
A78: Item | B78: Activity | J78: Prices (HK$)
A80: 20.1.3.3 | B80: Completion of piling works
A82: 20.1.3.3.1 | B82: Completion of all piling works for Bay NB16-01P | J82: $
A83: 20.1.3.3.2 | B83: Completion of all piling works for Bay NB16-02P | J83: $
A84: 20.1.3.3.3 | B84: Completion of all piling works for Bay NB16-03P | J84: $
A85: 20.1.3.3.4 | B85: Completion of all piling works for Bay NB16-04P | J85: $
A86: 20.1.3.3.5 | B86: Completion of all piling works for Bay NB16-05P | J86: $
A87: 20.1.3.3.6 | B87: Completion of all piling works for Bay NB16-06P | J87: $
A88: 20.1.3.3.7 | B88: Completion of all piling works for Bay NB16-07P | J88: $
A89: 20.1.3.3.8 | B89: Completion of all piling works for Bay NB16-08P | J89: $
A90: 20.1.3.3.9 | B90: Completion of all piling works for Bay NB16-09P | J90: $
A91: 20.1.3.3.10 | B91: Completion of all piling works for Bay NB16-10P | J91: $
A92: 20.1.3.3.11 | B92: Completion of all piling works for Bay NB16-11P | J92: $
A93: 20.1.3.3.12 | B93: Completion of all piling works for Bay NB16-12P | J93: $
... A103: 20.1.3.3.22 | B103: Completion of all piling works for Bay NB16-22P | J103: $
A105: 20.1.4 | B105: Pile tests
A107: 20.1.4.1 | B107: Completion of all pile tests | J107: $
I136: Total carried to collection | J136: $
A137: Item | B137: Activity | J137: Prices (HK$)
A139: 20.2 | B139: Substructure
A141: 20.2.1 | B141: Excavation for pile cap
A143: 20.2.1.1 | B143: Completion of excavation of pile cap for Bay NB16-01P | J143: $
A144: 20.2.1.2 | B144: Completion of excavation of pile cap for Bay NB16-02P | J144: $
A145: 20.2.1.3 | B145: Completion of excavation of pile cap for Bay NB16-03P | J145: $
A146: 20.2.1.4 | B146: Completion of excavation of pile cap for Bay NB16-04P | J146: $
A147: 20.2.1.5 | B147: Completion of excavation of pile cap for Bay NB16-05P | J147: $
A148: 20.2.1.6 | B148: Completion of excavation of pile cap for Bay NB16-06P | J148: $
A149: 20.2.1.7 | B149: Completion of excavation of pile cap for Bay NB16-07P | J149: $
A150: 20.2.1.8 | B150: Completion of excavation of pile cap for Bay NB16-08P | J150: $
A151: 20.2.1.9 | B151: Completion of excavation of pile cap for Bay NB16-09P | J151: $
A152: 20.2.1.10 | B152: Completion of excavation of pile cap for Bay NB16-10P | J152: $
A153: 20.2.1.11 | B153: Completion of excavation of pile cap for Bay NB16-11P | J153: $
A154: 20.2.1.12 | B154: Completion of excavation of pile cap for Bay NB16-12P | J154: $
... A164: 20.2.1.22 | B164: Completion of excavation of pile cap for Bay NB16-22P | J164: $
A166: 20.2.2 | B166: Fixing of reinforcement
A168: 20.2.2.1 | B168: Completion of fixing of reinforcement of pile cap and stem wall for Bay NB16-01P | J168: $
A169: 20.2.2.2 | B169: Completion of fixing of reinforcement of pile cap and stem wall for Bay NB16-02P | J169: $
A170: 20.2.2.3 | B170: Completion of fixing of reinforcement of pile cap and stem wall for Bay NB16-03P | J170: $
A171: 20.2.2.4 | B171: Completion of fixing of reinforcement of pile cap and stem wall for Bay NB16-04P | J171: $
A172: 20.2.2.5 | B172: Completion of fixing of reinforcement of pile cap and stem wall for Bay NB16-05P | J172: $
A173: 20.2.2.6 | B173: Completion of fixing of reinforcement of pile cap and stem wall for Bay NB16-06P | J173: $
A174: 20.2.2.7 | B174: Completion of fixing of reinforcement of pile cap and stem wall for Bay NB16-07P | J174: $
A175: 20.2.2.8 | B175: Completion of fixing of reinforcement of pile cap and stem wall for Bay NB16-08P | J175: $
A176: 20.2.2.9 | B176: Completion of fixing of reinforcement of pile cap and stem wall for Bay NB16-09P | J176: $
A177: 20.2.2.10 | B177: Completion of fixing of reinforcement of pile cap and stem wall for Bay NB16-10P | J177: $
A178: 20.2.2.11 | B178: Completion of fixing of reinforcement of pile cap and stem wall for Bay NB16-11P | J178: $
A179: 20.2.2.12 | B179: Completion of fixing of reinforcement of pile cap and stem wall for Bay NB16-12P | J179: $
... A189: 20.2.2.22 | B189: Completion of fixing of reinforcement of pile cap and stem wall for Bay NB16-22P | J189: $
I195: Total carried to collection | J195: $
A196: Item | B196: Activity | J196: Prices (HK$)
A198: 20.2.3 | B198: Completion of pile caps with stem wall
A200: 20.2.3.1 | B200: Completion of all pile caps with stem wall and movement joints for Bay NB16-01P | J200: $
A201: 20.2.3.2 | B201: Completion of all pile caps with stem wall and movement joints for Bay NB16-02P | J201: $
A202: 20.2.3.3 | B202: Completion of all pile caps with stem wall and movement joints for Bay NB16-03P | J202: $
A203: 20.2.3.4 | B203: Completion of all pile caps with stem wall and movement joints for Bay NB16-04P | J203: $
A204: 20.2.3.5 | B204: Completion of all pile caps with stem wall and movement joints for Bay NB16-05P | J204: $
A205: 20.2.3.6 | B205: Completion of all pile caps with stem wall and movement joints for Bay NB16-06P | J205: $
A206: 20.2.3.7 | B206: Completion of all pile caps with stem wall and movement joints for Bay NB16-07P | J206: $
...

Sheet A21
A2: THE GOVERNMENT OF THE HONG KONG SPECIAL ADMINISTRATIVE REGION
A4: HIGHWAYS DEPARTMENT
A5: MAJOR WORKS PROJECT MANAGEMENT OFFICE
A7: CONTRACT NO. HY/2021/06
A8: RETROFITTING OF NOISE BARRIERS ON PO LAM ROAD NORTH AND PO NING ROAD
A10: ACTIVITY SCHEDULE
A12: Schedule No. 21 - Noise Semi-enclosure SE01
A14: Item | B14: Activity | J14: Prices (HK$)
A16: 21 | B16: Noise Semi-enclosure SE01
A18: 21.1 | B18: Piling Works
A20: 21.1.1 | B20: Establishment of piling plant | J20: $
A22: 21.1.2 | B22: Pre-drilling works | J22: $
A24: 21.1.3 | B24: Piling
A26: 21.1.3.1 | B26: Excavation of piles
A28: 21.1.3.1.1 | B28: Completion of excavation of piles for Bay SE01-01P | J28: $
A29: 21.1.3.1.2 | B29: Completion of excavation of piles for Bay SE01-02P | J29: $
A30: 21.1.3.1.3 | B30: Completion of excavation of piles for Bay SE01-03P | J30: $
A31: 21.1.3.1.4 | B31: Completion of excavation of piles for Bay SE01-04P | J31: $
A32: 21.1.3.1.5 | B32: Completion of excavation of piles for Bay SE01-05P | J32: $
A33: 21.1.3.1.6 | B33: Completion of excavation of piles for Bay SE01-101P | J33: $
A34: 21.1.3.1.7 | B34: Completion of excavation of piles for Bay SE01-102P | J34: $
A35: 21.1.3.1.8 | B35: Completion of excavation of piles for Bay SE01-103P | J35: $
A36: 21.1.3.1.9 | B36: Completion of excavation of piles for Bay SE01-104P | J36: $
A37: 21.1.3.1.10 | B37: Completion of excavation of piles for Bay SE01-105P | J37: $
A39: 21.1.3.2 | B39: Installation of reinforcement for piles
A41: 21.1.3.2.1 | B41: Completion of installation of reinforcement of piles for Bay SE01-01P | J41: $
A42: 21.1.3.2.2 | B42: Completion of installation of reinforcement of piles for Bay SE01-02P | J42: $
A43: 21.1.3.2.3 | B43: Completion of installation of reinforcement of piles for Bay SE01-03P | J43: $
A44: 21.1.3.2.4 | B44: Completion of installation of reinforcement of piles for Bay SE01-04P | J44: $
A45: 21.1.3.2.5 | B45: Completion of installation of reinforcement of piles for Bay SE01-05P | J45: $
A46: 21.1.3.2.6 | B46: Completion of installation of reinforcement of piles for Bay SE01-101P | J46: $
A47: 21.1.3.2.7 | B47: Completion of installation of reinforcement of piles for Bay SE01-102P | J47: $
A48: 21.1.3.2.8 | B48: Completion of installation of reinforcement of piles for Bay SE01-103P | J48: $
A49: 21.1.3.2.9 | B49: Completion of installation of reinforcement of piles for Bay SE01-104P | J49: $
A50: 21.1.3.2.10 | B50: Completion of installation of reinforcement of piles for Bay SE01-105P | J50: $
I76: Total carried to collection | J76: $
A77: Item | B77: Activity | J77: Prices (HK$)
A79: 21.1.3.3 | B79: Completion of piling works
A81: 21.1.3.3.1 | B81: Completion of all piling works for Bay SE01-01P | J81: $
A82: 21.1.3.3.2 | B82: Completion of all piling works for Bay SE01-02P | J82: $
A83: 21.1.3.3.3 | B83: Completion of all piling works for Bay SE01-03P | J83: $
A84: 21.1.3.3.4 | B84: Completion of all piling works for Bay SE01-04P | J84: $
A85: 21.1.3.3.5 | B85: Completion of all piling works for Bay SE01-05P | J85: $
A86: 21.1.3.3.6 | B86: Completion of all piling works for Bay SE01-101P | J86: $
A87: 21.1.3.3.7 | B87: Completion of all piling works for Bay SE01-102P | J87: $
A88: 21.1.3.3.8 | B88: Completion of all piling works for Bay SE01-103P | J88: $
A89: 21.1.3.3.9 | B89: Completion of all piling works for Bay SE01-104P | J89: $
A90: 21.1.3.3.10 | B90: Completion of all piling works for Bay SE01-105P | J90: $
A92: 21.1.4 | B92: Pile tests
A94: 21.1.4.1 | B94: Completion of all pile tests | J94: $
I139: Total carried to collection | J139: $
A140: Item | B140: Activity | J140: Prices (HK$)
A142: 21.2 | B142: Substructure
A144: 21.2.1 | B144: Excavation for pile cap
A146: 21.2.1.1 | B146: Completion of excavation of pile cap for Bay SE01-01P | J146: $
A147: 21.2.1.2 | B147: Completion of excavation of pile cap for Bay SE01-02P | J147: $
A148: 21.2.1.3 | B148: Completion of excavation of pile cap for Bay SE01-03P | J148: $
A149: 21.2.1.4 | B149: Completion of excavation of pile cap for Bay SE01-04P | J149: $
A150: 21.2.1.5 | B150: Completion of excavation of pile cap for Bay SE01-05P | J150: $
A151: 21.2.1.6 | B151: Completion of excavation of pile cap for Bay SE01-101P | J151: $
A152: 21.2.1.7 | B152: Completion of excavation of pile cap for Bay SE01-102P | J152: $
A153: 21.2.1.8 | B153: Completion of excavation of pile cap for Bay SE01-103P | J153: $
A154: 21.2.1.9 | B154: Completion of excavation of pile cap for Bay SE01-104P | J154: $
A155: 21.2.1.10 | B155: Completion of excavation of pile cap for Bay SE01-105P | J155: $
A157: 21.2.2 | B157: Fixing of reinforcement
A159: 21.2.2.1 | B159: Completion of fixing of reinforcement of pile cap and stem wall for Bay SE01-01P | J159: $
A160: 21.2.2.2 | B160: Completion of fixing of reinforcement of pile cap and stem wall for Bay SE01-02P | J160: $
A161: 21.2.2.3 | B161: Completion of fixing of reinforcement of pile cap and stem wall for Bay SE01-03P | J161: $
A162: 21.2.2.4 | B162: Completion of fixing of reinforcement of pile cap and stem wall for Bay SE01-04P | J162: $
A163: 21.2.2.5 | B163: Completion of fixing of reinforcement of pile cap and stem wall for Bay SE01-05P | J163: $
A164: 21.2.2.6 | B164: Completion of fixing of reinforcement of pile cap and stem wall for Bay SE01-101P | J164: $
A165: 21.2.2.7 | B165: Completion of fixing of reinforcement of pile cap and stem wall for Bay SE01-102P | J165: $
A166: 21.2.2.8 | B166: Completion of fixing of reinforcement of pile cap and stem wall for Bay SE01-103P | J166: $
A167: 21.2.2.9 | B167: Completion of fixing of reinforcement of pile cap and stem wall for Bay SE01-104P | J167: $
A168: 21.2.2.10 | B168: Completion of fixing of reinforcement of pile cap and stem wall for Bay SE01-105P | J168: $
A170: 21.2.3 | B170: Completion of pile caps with stem wall
A172: 21.2.3.1 | B172: Completion of all pile caps with stem wall and movement joints for Bay SE01-01P | J172: $
A173: 21.2.3.2 | B173: Completion of all pile caps with stem wall and movement joints for Bay SE01-02P | J173: $
A174: 21.2.3.3 | B174: Completion of all pile caps with stem wall and movement joints for Bay SE01-03P | J174: $
A175: 21.2.3.4 | B175: Completion of all pile caps with stem wall and movement joints for Bay SE01-04P | J175: $
A176: 21.2.3.5 | B176: Completion of all pile caps with stem wall and movement joints for Bay SE01-05P | J176: $
A177: 21.2.3.6 | B177: Completion of all pile caps with stem wall and movement joints for Bay SE01-101P | J177: $
A178: 21.2.3.7 | B178: Completion of all pile caps with stem wall and movement joints for Bay SE01-102P | J178: $
A179: 21.2.3.8 | B179: Completion of all pile caps with stem wall and movement joints for Bay SE01-103P | J179: $
A180: 21.2.3.9 | B180: Completion of all pile caps with stem wall and movement joints for Bay SE01-104P | J180: $
A181: 21.2.3.10 | B181: Completion of all pile caps with stem wall and movement joints for Bay SE01-105P | J181: $
I201: Total carried to collection | J201: $
A202: Item | B202: Activity | J202: Prices (HK$)
A204: 21.3 | B204: Superstructure
A206: 21.3.1 | B206: Installation of vertical posts for noise semi-enclosure
A208: 21.3.1.1 | B208: Completion of installation of vertical posts of noise semi-enclosure for Bay SE01-01P | J208: $
A209: 21.3.1.2 | B209: Completion of installation of vertical posts of noise semi-enclosure for Bay SE01-02P | J209: $
A210: 21.3.1.3 | B210: Completion of installation of vertical posts of noise semi-enclosure for Bay SE01-03P | J210: $
A211: 21.3.1.4 | B211: Completion of installation of vertical posts of noise semi-enclosure for Bay SE01-04P | J211: $
A212: 21.3.1.5 | B212: Completion of installation of vertical posts of noise semi-enclosure for Bay SE01-05P | J212: $
A213: 21.3.1.6 | B213: Completion of installation of vertical posts of noise semi-enclosure for Bay SE01-101P | J213: $
A214: 21.3.1.7 | B214: Completion of installation of vertical posts of noise semi-enclosure for Bay SE01-102P | J214: $
A215: 21.3.1.8 | B215: Completion of installation of vertical posts of noise semi-enclosure for Bay SE01-103P | J215: $
A216: 21.3.1.9 | B216: Completion of installation of vertical posts of noise semi-enclosure for Bay SE01-104P | J216: $
A217: 21.3.1.10 | B217: Completion of installation of vertical posts of noise semi-enclosure for Bay SE01-105P | J217: $
...

Sheet A25
A2: THE GOVERNMENT OF THE HONG KONG SPECIAL ADMINISTRATIVE REGION
A4: HIGHWAYS DEPARTMENT
A5: MAJOR WORKS PROJECT MANAGEMENT OFFICE
A7: CONTRACT NO. HY/2021/06
A8: RETROFITTING OF NOISE BARRIERS ON PO LAM ROAD NORTH AND PO NING ROAD
A10: ACTIVITY SCHEDULE
A12: Schedule No. 25 - Geotechnical Works
A14: Item | B14: Activity | J14: Prices (HK$)
A16: 25.1 | B16: Slopeworks
A18: 25.1.1 | B18: Sub-soil drains
A19: 25.1.1.1 | C19: perforated polyethelene pipe; 50mm diameter | J19: $
A21: 25.1.1.2 | C21: UPVC pipe; 50mm diameter | J21: $
A23: 25.1.1.3 | C23: U-channel; 225mm diameter without cover | J23: $
A25: 25.1.1.4 | C25: U-channel; 300mm diameter without cover | J25: $
A27: 25.1.1.5 | C27: U-channel; 375mm diameter without cover | J27: $
A29: 25.1.1.6 | C29: U-channel; 450mm diameter without cover | J29: $
A31: 25.1.1.7 | C31: stepped channel with apron; 300mm diameter | J31: $
A33: 25.1.2 | B33: Granular filters
A34: 25.1.2.1 | C34: grade 75 | J34: $
A36: 25.1.3 | B36: Geotextile filters
A37: 25.1.3.1 | C37: "Miradrain 5000" or product with equivalent performance | J37: $
A39: 25.1.3.2 | C39: non-woven polyprolene | J39: $
A41: 25.1.4 | B41: Earthworks
A42: 25.1.4.1 | C42: general excavation | J42: $
A44: 25.1.4.2 | C44: deposition of general fill material | J44: $
A46: 25.1.4.3 | C46: disposal of material | J46: $
A48: 25.1.4.4 | C48: compaction of general fill material | J48: $
A50: 25.1.5 | B50: Concrete
A51: 25.1.1.1 | C51: no-fines concrete | J51: $
A53: 25.1.6 | B53: Erosion Control Mats | J53: $
A55: 25.1.7 | B55: Wire mesh | J55: $
I76: Total carried to collection | J76: $
A77: Item | B77: Activity | J77: Prices (HK$)
B79: Collection from Page AS.S25/1 | J79: $
I139: Total Prices of Schedule No. 25 Carried to Grand Summary of the Activity Schedule | J139: $
